[{"id":1,"patientID":25,"date":"12/31/2020","result":23,"consultedBy":3,"consultedAt":3},
{"id":2,"patientID":27,"date":"12/27/2020","result":27,"consultedBy":2,"consultedAt":5},
{"id":3,"patientID":17,"date":"12/29/2020","result":13,"consultedBy":10,"consultedAt":1},
{"id":4,"patientID":39,"date":"12/11/2020","result":26,"consultedBy":5,"consultedAt":1},
{"id":5,"patientID":33,"date":"12/28/2020","result":87,"consultedBy":3,"consultedAt":3},
{"id":6,"patientID":79,"date":"12/21/2020","result":73,"consultedBy":1,"consultedAt":4},
{"id":7,"patientID":1,"date":"12/6/2020","result":72,"consultedBy":1,"consultedAt":8},
{"id":8,"patientID":42,"date":"12/13/2020","result":89,"consultedBy":3,"consultedAt":5},
{"id":9,"patientID":6,"date":"1/2/2021","result":68,"consultedBy":3,"consultedAt":9},
{"id":10,"patientID":89,"date":"12/28/2020","result":93,"consultedBy":8,"consultedAt":5},
{"id":11,"patientID":53,"date":"12/3/2020","result":58,"consultedBy":1,"consultedAt":10},
{"id":12,"patientID":64,"date":"12/21/2020","result":9,"consultedBy":8,"consultedAt":7},
{"id":13,"patientID":15,"date":"12/3/2020","result":3,"consultedBy":6,"consultedAt":3},
{"id":14,"patientID":83,"date":"12/12/2020","result":58,"consultedBy":7,"consultedAt":10},
{"id":15,"patientID":30,"date":"12/15/2020","result":60,"consultedBy":4,"consultedAt":3},
{"id":16,"patientID":21,"date":"12/18/2020","result":32,"consultedBy":5,"consultedAt":5},
{"id":17,"patientID":81,"date":"12/3/2020","result":49,"consultedBy":5,"consultedAt":2},
{"id":18,"patientID":36,"date":"12/1/2020","result":67,"consultedBy":10,"consultedAt":3},
{"id":19,"patientID":67,"date":"12/25/2020","result":29,"consultedBy":1,"consultedAt":9},
{"id":20,"patientID":27,"date":"12/3/2020","result":74,"consultedBy":1,"consultedAt":5},
{"id":21,"patientID":74,"date":"12/16/2020","result":35,"consultedBy":4,"consultedAt":9},
{"id":22,"patientID":38,"date":"12/28/2020","result":67,"consultedBy":3,"consultedAt":7},
{"id":23,"patientID":16,"date":"12/19/2020","result":19,"consultedBy":6,"consultedAt":2},
{"id":24,"patientID":29,"date":"12/10/2020","result":82,"consultedBy":6,"consultedAt":2},
{"id":25,"patientID":29,"date":"1/1/2021","result":98,"consultedBy":5,"consultedAt":10},
{"id":26,"patientID":69,"date":"12/16/2020","result":8,"consultedBy":3,"consultedAt":9},
{"id":27,"patientID":33,"date":"12/24/2020","result":80,"consultedBy":2,"consultedAt":3},
{"id":28,"patientID":26,"date":"12/27/2020","result":31,"consultedBy":1,"consultedAt":10},
{"id":29,"patientID":86,"date":"12/29/2020","result":84,"consultedBy":3,"consultedAt":6},
{"id":30,"patientID":96,"date":"12/21/2020","result":68,"consultedBy":10,"consultedAt":8},
{"id":31,"patientID":31,"date":"12/28/2020","result":73,"consultedBy":6,"consultedAt":3},
{"id":32,"patientID":58,"date":"12/13/2020","result":87,"consultedBy":6,"consultedAt":9},
{"id":33,"patientID":27,"date":"12/6/2020","result":82,"consultedBy":6,"consultedAt":8},
{"id":34,"patientID":52,"date":"12/16/2020","result":92,"consultedBy":5,"consultedAt":2},
{"id":35,"patientID":39,"date":"12/30/2020","result":7,"consultedBy":1,"consultedAt":2},
{"id":36,"patientID":28,"date":"12/7/2020","result":17,"consultedBy":8,"consultedAt":3},
{"id":37,"patientID":57,"date":"12/29/2020","result":39,"consultedBy":7,"consultedAt":3},
{"id":38,"patientID":35,"date":"12/3/2020","result":77,"consultedBy":5,"consultedAt":6},
{"id":39,"patientID":62,"date":"1/2/2021","result":55,"consultedBy":8,"consultedAt":6},
{"id":40,"patientID":61,"date":"12/18/2020","result":1,"consultedBy":9,"consultedAt":10},
{"id":41,"patientID":67,"date":"12/6/2020","result":88,"consultedBy":3,"consultedAt":5},
{"id":42,"patientID":3,"date":"12/4/2020","result":19,"consultedBy":6,"consultedAt":5},
{"id":43,"patientID":92,"date":"12/2/2020","result":31,"consultedBy":9,"consultedAt":6},
{"id":44,"patientID":60,"date":"12/10/2020","result":85,"consultedBy":7,"consultedAt":6},
{"id":45,"patientID":67,"date":"12/29/2020","result":18,"consultedBy":1,"consultedAt":5},
{"id":46,"patientID":44,"date":"12/15/2020","result":72,"consultedBy":8,"consultedAt":8},
{"id":47,"patientID":2,"date":"12/24/2020","result":12,"consultedBy":8,"consultedAt":1},
{"id":48,"patientID":57,"date":"1/1/2021","result":61,"consultedBy":8,"consultedAt":2},
{"id":49,"patientID":67,"date":"1/1/2021","result":87,"consultedBy":5,"consultedAt":6},
{"id":50,"patientID":97,"date":"12/19/2020","result":65,"consultedBy":2,"consultedAt":7},
{"id":51,"patientID":29,"date":"12/2/2020","result":95,"consultedBy":3,"consultedAt":2},
{"id":52,"patientID":87,"date":"12/14/2020","result":88,"consultedBy":3,"consultedAt":10},
{"id":53,"patientID":99,"date":"12/27/2020","result":51,"consultedBy":8,"consultedAt":1},
{"id":54,"patientID":13,"date":"12/3/2020","result":44,"consultedBy":9,"consultedAt":3},
{"id":55,"patientID":58,"date":"12/15/2020","result":35,"consultedBy":4,"consultedAt":8},
{"id":56,"patientID":83,"date":"12/16/2020","result":10,"consultedBy":6,"consultedAt":4},
{"id":57,"patientID":9,"date":"12/29/2020","result":87,"consultedBy":7,"consultedAt":2},
{"id":58,"patientID":6,"date":"12/15/2020","result":64,"consultedBy":4,"consultedAt":5},
{"id":59,"patientID":20,"date":"12/21/2020","result":67,"consultedBy":4,"consultedAt":3},
{"id":60,"patientID":53,"date":"12/24/2020","result":17,"consultedBy":10,"consultedAt":6},
{"id":61,"patientID":4,"date":"12/4/2020","result":68,"consultedBy":2,"consultedAt":2},
{"id":62,"patientID":73,"date":"12/19/2020","result":13,"consultedBy":7,"consultedAt":7},
{"id":63,"patientID":56,"date":"12/23/2020","result":35,"consultedBy":3,"consultedAt":4},
{"id":64,"patientID":27,"date":"1/1/2021","result":56,"consultedBy":4,"consultedAt":1},
{"id":65,"patientID":14,"date":"12/9/2020","result":23,"consultedBy":9,"consultedAt":9},
{"id":66,"patientID":85,"date":"12/22/2020","result":43,"consultedBy":1,"consultedAt":10},
{"id":67,"patientID":54,"date":"12/4/2020","result":8,"consultedBy":10,"consultedAt":9},
{"id":68,"patientID":57,"date":"1/2/2021","result":36,"consultedBy":5,"consultedAt":8},
{"id":69,"patientID":37,"date":"12/24/2020","result":41,"consultedBy":9,"consultedAt":6},
{"id":70,"patientID":48,"date":"12/11/2020","result":73,"consultedBy":6,"consultedAt":1},
{"id":71,"patientID":91,"date":"12/14/2020","result":62,"consultedBy":1,"consultedAt":6},
{"id":72,"patientID":8,"date":"12/15/2020","result":96,"consultedBy":1,"consultedAt":5},
{"id":73,"patientID":58,"date":"12/14/2020","result":38,"consultedBy":4,"consultedAt":7},
{"id":74,"patientID":99,"date":"12/24/2020","result":13,"consultedBy":5,"consultedAt":9},
{"id":75,"patientID":74,"date":"12/15/2020","result":35,"consultedBy":3,"consultedAt":9},
{"id":76,"patientID":72,"date":"12/17/2020","result":73,"consultedBy":4,"consultedAt":7},
{"id":77,"patientID":75,"date":"12/13/2020","result":88,"consultedBy":6,"consultedAt":4},
{"id":78,"patientID":96,"date":"12/12/2020","result":58,"consultedBy":3,"consultedAt":4},
{"id":79,"patientID":19,"date":"12/19/2020","result":91,"consultedBy":6,"consultedAt":1},
{"id":80,"patientID":19,"date":"12/10/2020","result":95,"consultedBy":1,"consultedAt":3},
{"id":81,"patientID":1,"date":"12/29/2020","result":70,"consultedBy":7,"consultedAt":7},
{"id":82,"patientID":42,"date":"12/31/2020","result":73,"consultedBy":5,"consultedAt":8},
{"id":83,"patientID":31,"date":"12/26/2020","result":66,"consultedBy":9,"consultedAt":9},
{"id":84,"patientID":73,"date":"12/22/2020","result":1,"consultedBy":2,"consultedAt":9},
{"id":85,"patientID":83,"date":"12/30/2020","result":83,"consultedBy":7,"consultedAt":4},
{"id":86,"patientID":9,"date":"1/2/2021","result":69,"consultedBy":9,"consultedAt":1},
{"id":87,"patientID":47,"date":"12/1/2020","result":46,"consultedBy":6,"consultedAt":5},
{"id":88,"patientID":51,"date":"12/7/2020","result":86,"consultedBy":4,"consultedAt":8},
{"id":89,"patientID":87,"date":"12/12/2020","result":27,"consultedBy":4,"consultedAt":10},
{"id":90,"patientID":83,"date":"12/29/2020","result":35,"consultedBy":8,"consultedAt":1},
{"id":91,"patientID":40,"date":"12/31/2020","result":29,"consultedBy":8,"consultedAt":4},
{"id":92,"patientID":93,"date":"12/5/2020","result":35,"consultedBy":6,"consultedAt":5},
{"id":93,"patientID":13,"date":"12/23/2020","result":29,"consultedBy":7,"consultedAt":2},
{"id":94,"patientID":63,"date":"12/30/2020","result":25,"consultedBy":7,"consultedAt":10},
{"id":95,"patientID":39,"date":"12/23/2020","result":97,"consultedBy":1,"consultedAt":3},
{"id":96,"patientID":37,"date":"1/1/2021","result":49,"consultedBy":8,"consultedAt":6},
{"id":97,"patientID":74,"date":"12/28/2020","result":14,"consultedBy":10,"consultedAt":9},
{"id":98,"patientID":17,"date":"12/10/2020","result":60,"consultedBy":8,"consultedAt":8},
{"id":99,"patientID":58,"date":"12/21/2020","result":53,"consultedBy":5,"consultedAt":3},
{"id":100,"patientID":97,"date":"12/15/2020","result":48,"consultedBy":8,"consultedAt":7},
{"id":101,"patientID":31,"date":"12/29/2020","result":58,"consultedBy":9,"consultedAt":10},
{"id":102,"patientID":32,"date":"12/6/2020","result":77,"consultedBy":4,"consultedAt":8},
{"id":103,"patientID":25,"date":"12/27/2020","result":8,"consultedBy":4,"consultedAt":7},
{"id":104,"patientID":77,"date":"12/11/2020","result":83,"consultedBy":2,"consultedAt":3},
{"id":105,"patientID":18,"date":"12/8/2020","result":11,"consultedBy":9,"consultedAt":3},
{"id":106,"patientID":47,"date":"12/10/2020","result":88,"consultedBy":2,"consultedAt":9},
{"id":107,"patientID":21,"date":"1/2/2021","result":35,"consultedBy":5,"consultedAt":5},
{"id":108,"patientID":71,"date":"12/28/2020","result":37,"consultedBy":2,"consultedAt":9},
{"id":109,"patientID":78,"date":"1/2/2021","result":60,"consultedBy":6,"consultedAt":1},
{"id":110,"patientID":98,"date":"12/2/2020","result":14,"consultedBy":5,"consultedAt":8},
{"id":111,"patientID":10,"date":"12/5/2020","result":96,"consultedBy":5,"consultedAt":3},
{"id":112,"patientID":1,"date":"12/17/2020","result":43,"consultedBy":4,"consultedAt":7},
{"id":113,"patientID":7,"date":"12/23/2020","result":6,"consultedBy":2,"consultedAt":9},
{"id":114,"patientID":14,"date":"12/1/2020","result":39,"consultedBy":1,"consultedAt":5},
{"id":115,"patientID":59,"date":"12/24/2020","result":82,"consultedBy":2,"consultedAt":3},
{"id":116,"patientID":95,"date":"12/15/2020","result":51,"consultedBy":1,"consultedAt":5},
{"id":117,"patientID":48,"date":"12/29/2020","result":96,"consultedBy":6,"consultedAt":4},
{"id":118,"patientID":96,"date":"1/2/2021","result":92,"consultedBy":7,"consultedAt":1},
{"id":119,"patientID":3,"date":"12/6/2020","result":2,"consultedBy":2,"consultedAt":3},
{"id":120,"patientID":7,"date":"1/2/2021","result":44,"consultedBy":2,"consultedAt":8},
{"id":121,"patientID":36,"date":"12/22/2020","result":10,"consultedBy":6,"consultedAt":6},
{"id":122,"patientID":8,"date":"1/1/2021","result":21,"consultedBy":6,"consultedAt":3},
{"id":123,"patientID":62,"date":"12/31/2020","result":44,"consultedBy":6,"consultedAt":2},
{"id":124,"patientID":64,"date":"12/27/2020","result":17,"consultedBy":10,"consultedAt":8},
{"id":125,"patientID":90,"date":"12/28/2020","result":17,"consultedBy":4,"consultedAt":4},
{"id":126,"patientID":46,"date":"12/29/2020","result":36,"consultedBy":10,"consultedAt":8},
{"id":127,"patientID":12,"date":"12/24/2020","result":71,"consultedBy":2,"consultedAt":3},
{"id":128,"patientID":55,"date":"12/2/2020","result":67,"consultedBy":2,"consultedAt":5},
{"id":129,"patientID":72,"date":"12/4/2020","result":65,"consultedBy":4,"consultedAt":6},
{"id":130,"patientID":38,"date":"12/3/2020","result":7,"consultedBy":2,"consultedAt":7},
{"id":131,"patientID":20,"date":"12/4/2020","result":3,"consultedBy":5,"consultedAt":1},
{"id":132,"patientID":37,"date":"12/3/2020","result":8,"consultedBy":6,"consultedAt":4},
{"id":133,"patientID":59,"date":"12/1/2020","result":72,"consultedBy":9,"consultedAt":1},
{"id":134,"patientID":22,"date":"12/26/2020","result":11,"consultedBy":5,"consultedAt":7},
{"id":135,"patientID":72,"date":"12/12/2020","result":18,"consultedBy":4,"consultedAt":9},
{"id":136,"patientID":94,"date":"12/7/2020","result":57,"consultedBy":10,"consultedAt":8},
{"id":137,"patientID":2,"date":"12/1/2020","result":57,"consultedBy":9,"consultedAt":3},
{"id":138,"patientID":35,"date":"12/20/2020","result":26,"consultedBy":9,"consultedAt":9},
{"id":139,"patientID":68,"date":"12/5/2020","result":27,"consultedBy":5,"consultedAt":9},
{"id":140,"patientID":35,"date":"12/19/2020","result":95,"consultedBy":2,"consultedAt":4},
{"id":141,"patientID":87,"date":"12/15/2020","result":17,"consultedBy":6,"consultedAt":4},
{"id":142,"patientID":58,"date":"12/18/2020","result":24,"consultedBy":7,"consultedAt":9},
{"id":143,"patientID":63,"date":"12/22/2020","result":100,"consultedBy":5,"consultedAt":8},
{"id":144,"patientID":79,"date":"1/2/2021","result":85,"consultedBy":4,"consultedAt":4},
{"id":145,"patientID":40,"date":"12/10/2020","result":78,"consultedBy":5,"consultedAt":8},
{"id":146,"patientID":79,"date":"12/27/2020","result":52,"consultedBy":4,"consultedAt":5},
{"id":147,"patientID":90,"date":"12/5/2020","result":83,"consultedBy":10,"consultedAt":1},
{"id":148,"patientID":55,"date":"12/30/2020","result":18,"consultedBy":6,"consultedAt":5},
{"id":149,"patientID":96,"date":"12/28/2020","result":26,"consultedBy":10,"consultedAt":7},
{"id":150,"patientID":59,"date":"12/28/2020","result":69,"consultedBy":9,"consultedAt":5},
{"id":151,"patientID":15,"date":"1/2/2021","result":36,"consultedBy":10,"consultedAt":5},
{"id":152,"patientID":43,"date":"12/23/2020","result":93,"consultedBy":7,"consultedAt":4},
{"id":153,"patientID":87,"date":"12/19/2020","result":26,"consultedBy":2,"consultedAt":8},
{"id":154,"patientID":61,"date":"12/14/2020","result":56,"consultedBy":3,"consultedAt":1},
{"id":155,"patientID":72,"date":"12/28/2020","result":77,"consultedBy":10,"consultedAt":5},
{"id":156,"patientID":42,"date":"12/4/2020","result":10,"consultedBy":1,"consultedAt":7},
{"id":157,"patientID":97,"date":"12/27/2020","result":19,"consultedBy":3,"consultedAt":2},
{"id":158,"patientID":45,"date":"12/20/2020","result":100,"consultedBy":7,"consultedAt":4},
{"id":159,"patientID":86,"date":"12/28/2020","result":80,"consultedBy":6,"consultedAt":1},
{"id":160,"patientID":87,"date":"12/21/2020","result":61,"consultedBy":6,"consultedAt":9},
{"id":161,"patientID":96,"date":"12/27/2020","result":44,"consultedBy":10,"consultedAt":2},
{"id":162,"patientID":27,"date":"12/1/2020","result":6,"consultedBy":5,"consultedAt":9},
{"id":163,"patientID":78,"date":"12/7/2020","result":9,"consultedBy":5,"consultedAt":8},
{"id":164,"patientID":70,"date":"12/31/2020","result":76,"consultedBy":9,"consultedAt":10},
{"id":165,"patientID":96,"date":"12/28/2020","result":78,"consultedBy":2,"consultedAt":1},
{"id":166,"patientID":7,"date":"12/8/2020","result":36,"consultedBy":8,"consultedAt":7},
{"id":167,"patientID":1,"date":"12/8/2020","result":2,"consultedBy":1,"consultedAt":5},
{"id":168,"patientID":91,"date":"12/9/2020","result":64,"consultedBy":8,"consultedAt":10},
{"id":169,"patientID":28,"date":"12/3/2020","result":18,"consultedBy":10,"consultedAt":1},
{"id":170,"patientID":41,"date":"12/22/2020","result":3,"consultedBy":7,"consultedAt":8},
{"id":171,"patientID":79,"date":"12/17/2020","result":92,"consultedBy":10,"consultedAt":9},
{"id":172,"patientID":43,"date":"12/25/2020","result":72,"consultedBy":6,"consultedAt":4},
{"id":173,"patientID":31,"date":"12/9/2020","result":29,"consultedBy":5,"consultedAt":5},
{"id":174,"patientID":64,"date":"12/11/2020","result":88,"consultedBy":5,"consultedAt":7},
{"id":175,"patientID":12,"date":"1/2/2021","result":89,"consultedBy":3,"consultedAt":7},
{"id":176,"patientID":47,"date":"12/19/2020","result":23,"consultedBy":5,"consultedAt":7},
{"id":177,"patientID":53,"date":"12/28/2020","result":24,"consultedBy":5,"consultedAt":4},
{"id":178,"patientID":74,"date":"12/26/2020","result":72,"consultedBy":4,"consultedAt":4},
{"id":179,"patientID":85,"date":"12/27/2020","result":78,"consultedBy":9,"consultedAt":2},
{"id":180,"patientID":16,"date":"12/27/2020","result":29,"consultedBy":9,"consultedAt":2},
{"id":181,"patientID":97,"date":"12/10/2020","result":45,"consultedBy":9,"consultedAt":8},
{"id":182,"patientID":67,"date":"12/4/2020","result":62,"consultedBy":5,"consultedAt":4},
{"id":183,"patientID":68,"date":"12/11/2020","result":74,"consultedBy":5,"consultedAt":8},
{"id":184,"patientID":37,"date":"12/8/2020","result":35,"consultedBy":9,"consultedAt":6},
{"id":185,"patientID":52,"date":"12/5/2020","result":51,"consultedBy":4,"consultedAt":1},
{"id":186,"patientID":61,"date":"12/5/2020","result":71,"consultedBy":8,"consultedAt":8},
{"id":187,"patientID":63,"date":"12/22/2020","result":63,"consultedBy":5,"consultedAt":9},
{"id":188,"patientID":60,"date":"12/21/2020","result":61,"consultedBy":5,"consultedAt":4},
{"id":189,"patientID":6,"date":"12/22/2020","result":62,"consultedBy":9,"consultedAt":7},
{"id":190,"patientID":11,"date":"12/21/2020","result":53,"consultedBy":1,"consultedAt":1},
{"id":191,"patientID":62,"date":"12/25/2020","result":39,"consultedBy":9,"consultedAt":3},
{"id":192,"patientID":46,"date":"12/30/2020","result":12,"consultedBy":9,"consultedAt":9},
{"id":193,"patientID":54,"date":"12/31/2020","result":76,"consultedBy":10,"consultedAt":8},
{"id":194,"patientID":38,"date":"12/2/2020","result":20,"consultedBy":7,"consultedAt":7},
{"id":195,"patientID":34,"date":"12/7/2020","result":41,"consultedBy":2,"consultedAt":9},
{"id":196,"patientID":17,"date":"12/6/2020","result":68,"consultedBy":9,"consultedAt":3},
{"id":197,"patientID":57,"date":"12/11/2020","result":99,"consultedBy":1,"consultedAt":7},
{"id":198,"patientID":16,"date":"12/4/2020","result":54,"consultedBy":8,"consultedAt":4},
{"id":199,"patientID":85,"date":"12/20/2020","result":10,"consultedBy":9,"consultedAt":10},
{"id":200,"patientID":57,"date":"12/14/2020","result":50,"consultedBy":5,"consultedAt":2},
{"id":201,"patientID":48,"date":"12/7/2020","result":3,"consultedBy":6,"consultedAt":5},
{"id":202,"patientID":39,"date":"12/11/2020","result":41,"consultedBy":5,"consultedAt":8},
{"id":203,"patientID":44,"date":"12/21/2020","result":87,"consultedBy":9,"consultedAt":7},
{"id":204,"patientID":40,"date":"12/28/2020","result":72,"consultedBy":8,"consultedAt":1},
{"id":205,"patientID":68,"date":"12/10/2020","result":66,"consultedBy":3,"consultedAt":2},
{"id":206,"patientID":62,"date":"12/20/2020","result":40,"consultedBy":10,"consultedAt":7},
{"id":207,"patientID":97,"date":"12/6/2020","result":82,"consultedBy":8,"consultedAt":1},
{"id":208,"patientID":16,"date":"12/6/2020","result":19,"consultedBy":6,"consultedAt":4},
{"id":209,"patientID":79,"date":"12/3/2020","result":44,"consultedBy":2,"consultedAt":5},
{"id":210,"patientID":69,"date":"12/7/2020","result":72,"consultedBy":8,"consultedAt":3},
{"id":211,"patientID":41,"date":"12/8/2020","result":95,"consultedBy":1,"consultedAt":9},
{"id":212,"patientID":1,"date":"12/4/2020","result":39,"consultedBy":9,"consultedAt":1},
{"id":213,"patientID":37,"date":"1/2/2021","result":85,"consultedBy":2,"consultedAt":1},
{"id":214,"patientID":98,"date":"12/10/2020","result":95,"consultedBy":2,"consultedAt":2},
{"id":215,"patientID":15,"date":"12/22/2020","result":78,"consultedBy":9,"consultedAt":3},
{"id":216,"patientID":17,"date":"12/17/2020","result":49,"consultedBy":10,"consultedAt":9},
{"id":217,"patientID":34,"date":"12/2/2020","result":42,"consultedBy":6,"consultedAt":9},
{"id":218,"patientID":56,"date":"12/5/2020","result":9,"consultedBy":2,"consultedAt":2},
{"id":219,"patientID":86,"date":"12/27/2020","result":27,"consultedBy":4,"consultedAt":10},
{"id":220,"patientID":86,"date":"12/20/2020","result":57,"consultedBy":9,"consultedAt":10},
{"id":221,"patientID":6,"date":"12/5/2020","result":59,"consultedBy":8,"consultedAt":3},
{"id":222,"patientID":34,"date":"12/28/2020","result":68,"consultedBy":9,"consultedAt":5},
{"id":223,"patientID":77,"date":"12/16/2020","result":92,"consultedBy":8,"consultedAt":4},
{"id":224,"patientID":85,"date":"12/10/2020","result":99,"consultedBy":6,"consultedAt":5},
{"id":225,"patientID":76,"date":"12/12/2020","result":90,"consultedBy":7,"consultedAt":6},
{"id":226,"patientID":90,"date":"12/12/2020","result":37,"consultedBy":6,"consultedAt":4},
{"id":227,"patientID":15,"date":"12/15/2020","result":97,"consultedBy":9,"consultedAt":6},
{"id":228,"patientID":75,"date":"1/2/2021","result":16,"consultedBy":9,"consultedAt":1},
{"id":229,"patientID":74,"date":"12/19/2020","result":75,"consultedBy":10,"consultedAt":2},
{"id":230,"patientID":32,"date":"12/27/2020","result":62,"consultedBy":7,"consultedAt":7},
{"id":231,"patientID":92,"date":"12/18/2020","result":70,"consultedBy":7,"consultedAt":3},
{"id":232,"patientID":76,"date":"12/19/2020","result":30,"consultedBy":2,"consultedAt":3},
{"id":233,"patientID":35,"date":"12/21/2020","result":33,"consultedBy":8,"consultedAt":4},
{"id":234,"patientID":65,"date":"12/28/2020","result":100,"consultedBy":4,"consultedAt":4},
{"id":235,"patientID":75,"date":"12/28/2020","result":18,"consultedBy":6,"consultedAt":4},
{"id":236,"patientID":26,"date":"12/5/2020","result":43,"consultedBy":6,"consultedAt":10},
{"id":237,"patientID":21,"date":"12/18/2020","result":23,"consultedBy":3,"consultedAt":3},
{"id":238,"patientID":94,"date":"12/4/2020","result":68,"consultedBy":3,"consultedAt":3},
{"id":239,"patientID":41,"date":"1/1/2021","result":66,"consultedBy":3,"consultedAt":5},
{"id":240,"patientID":80,"date":"12/3/2020","result":65,"consultedBy":4,"consultedAt":2},
{"id":241,"patientID":49,"date":"12/10/2020","result":41,"consultedBy":2,"consultedAt":9},
{"id":242,"patientID":10,"date":"12/16/2020","result":17,"consultedBy":8,"consultedAt":1},
{"id":243,"patientID":14,"date":"12/29/2020","result":8,"consultedBy":6,"consultedAt":10},
{"id":244,"patientID":65,"date":"12/22/2020","result":86,"consultedBy":6,"consultedAt":7},
{"id":245,"patientID":47,"date":"12/22/2020","result":66,"consultedBy":4,"consultedAt":2},
{"id":246,"patientID":34,"date":"12/13/2020","result":17,"consultedBy":9,"consultedAt":4},
{"id":247,"patientID":91,"date":"12/5/2020","result":49,"consultedBy":3,"consultedAt":2},
{"id":248,"patientID":72,"date":"12/19/2020","result":60,"consultedBy":5,"consultedAt":3},
{"id":249,"patientID":28,"date":"12/2/2020","result":9,"consultedBy":4,"consultedAt":9},
{"id":250,"patientID":84,"date":"12/5/2020","result":80,"consultedBy":1,"consultedAt":10},
{"id":251,"patientID":92,"date":"12/28/2020","result":46,"consultedBy":10,"consultedAt":3},
{"id":252,"patientID":25,"date":"12/30/2020","result":44,"consultedBy":1,"consultedAt":3},
{"id":253,"patientID":16,"date":"12/19/2020","result":96,"consultedBy":7,"consultedAt":3},
{"id":254,"patientID":1,"date":"12/21/2020","result":89,"consultedBy":6,"consultedAt":3},
{"id":255,"patientID":40,"date":"12/15/2020","result":87,"consultedBy":6,"consultedAt":3},
{"id":256,"patientID":32,"date":"12/18/2020","result":23,"consultedBy":9,"consultedAt":1},
{"id":257,"patientID":55,"date":"12/7/2020","result":70,"consultedBy":9,"consultedAt":10},
{"id":258,"patientID":4,"date":"12/4/2020","result":97,"consultedBy":8,"consultedAt":9},
{"id":259,"patientID":10,"date":"12/27/2020","result":68,"consultedBy":1,"consultedAt":3},
{"id":260,"patientID":71,"date":"12/17/2020","result":15,"consultedBy":6,"consultedAt":9},
{"id":261,"patientID":61,"date":"12/21/2020","result":14,"consultedBy":6,"consultedAt":5},
{"id":262,"patientID":9,"date":"12/1/2020","result":71,"consultedBy":8,"consultedAt":6},
{"id":263,"patientID":94,"date":"12/25/2020","result":15,"consultedBy":2,"consultedAt":1},
{"id":264,"patientID":73,"date":"12/11/2020","result":54,"consultedBy":6,"consultedAt":6},
{"id":265,"patientID":42,"date":"12/29/2020","result":54,"consultedBy":7,"consultedAt":2},
{"id":266,"patientID":7,"date":"12/3/2020","result":73,"consultedBy":5,"consultedAt":8},
{"id":267,"patientID":98,"date":"12/3/2020","result":26,"consultedBy":10,"consultedAt":1},
{"id":268,"patientID":12,"date":"12/30/2020","result":59,"consultedBy":6,"consultedAt":3},
{"id":269,"patientID":66,"date":"12/23/2020","result":63,"consultedBy":6,"consultedAt":7},
{"id":270,"patientID":57,"date":"12/2/2020","result":35,"consultedBy":3,"consultedAt":1},
{"id":271,"patientID":96,"date":"12/4/2020","result":87,"consultedBy":4,"consultedAt":10},
{"id":272,"patientID":5,"date":"12/24/2020","result":34,"consultedBy":3,"consultedAt":6},
{"id":273,"patientID":91,"date":"12/7/2020","result":73,"consultedBy":9,"consultedAt":9},
{"id":274,"patientID":17,"date":"12/29/2020","result":99,"consultedBy":8,"consultedAt":4},
{"id":275,"patientID":4,"date":"12/10/2020","result":55,"consultedBy":1,"consultedAt":8},
{"id":276,"patientID":13,"date":"12/4/2020","result":30,"consultedBy":10,"consultedAt":1},
{"id":277,"patientID":23,"date":"12/12/2020","result":76,"consultedBy":1,"consultedAt":3},
{"id":278,"patientID":69,"date":"12/2/2020","result":79,"consultedBy":10,"consultedAt":9},
{"id":279,"patientID":95,"date":"12/23/2020","result":31,"consultedBy":10,"consultedAt":5},
{"id":280,"patientID":57,"date":"12/20/2020","result":57,"consultedBy":5,"consultedAt":1},
{"id":281,"patientID":36,"date":"12/16/2020","result":63,"consultedBy":9,"consultedAt":6},
{"id":282,"patientID":70,"date":"12/15/2020","result":68,"consultedBy":4,"consultedAt":6},
{"id":283,"patientID":17,"date":"12/7/2020","result":30,"consultedBy":4,"consultedAt":6},
{"id":284,"patientID":74,"date":"12/31/2020","result":5,"consultedBy":8,"consultedAt":4},
{"id":285,"patientID":24,"date":"12/26/2020","result":69,"consultedBy":10,"consultedAt":4},
{"id":286,"patientID":94,"date":"12/3/2020","result":68,"consultedBy":2,"consultedAt":4},
{"id":287,"patientID":61,"date":"12/5/2020","result":77,"consultedBy":5,"consultedAt":5},
{"id":288,"patientID":58,"date":"12/4/2020","result":32,"consultedBy":2,"consultedAt":2},
{"id":289,"patientID":42,"date":"12/13/2020","result":2,"consultedBy":5,"consultedAt":5},
{"id":290,"patientID":40,"date":"12/29/2020","result":61,"consultedBy":8,"consultedAt":8},
{"id":291,"patientID":48,"date":"12/28/2020","result":63,"consultedBy":3,"consultedAt":1},
{"id":292,"patientID":40,"date":"12/9/2020","result":45,"consultedBy":8,"consultedAt":9},
{"id":293,"patientID":85,"date":"1/1/2021","result":6,"consultedBy":10,"consultedAt":1},
{"id":294,"patientID":30,"date":"12/19/2020","result":68,"consultedBy":9,"consultedAt":4},
{"id":295,"patientID":45,"date":"12/4/2020","result":96,"consultedBy":4,"consultedAt":3},
{"id":296,"patientID":48,"date":"12/12/2020","result":99,"consultedBy":6,"consultedAt":8},
{"id":297,"patientID":70,"date":"12/18/2020","result":92,"consultedBy":8,"consultedAt":7},
{"id":298,"patientID":85,"date":"12/6/2020","result":9,"consultedBy":9,"consultedAt":1},
{"id":299,"patientID":48,"date":"12/28/2020","result":5,"consultedBy":9,"consultedAt":9},
{"id":300,"patientID":11,"date":"12/24/2020","result":61,"consultedBy":9,"consultedAt":8},
{"id":301,"patientID":87,"date":"12/15/2020","result":98,"consultedBy":10,"consultedAt":6},
{"id":302,"patientID":9,"date":"12/15/2020","result":42,"consultedBy":5,"consultedAt":5},
{"id":303,"patientID":55,"date":"12/27/2020","result":32,"consultedBy":4,"consultedAt":8},
{"id":304,"patientID":86,"date":"12/23/2020","result":23,"consultedBy":3,"consultedAt":9},
{"id":305,"patientID":5,"date":"12/19/2020","result":88,"consultedBy":9,"consultedAt":9},
{"id":306,"patientID":9,"date":"12/11/2020","result":94,"consultedBy":10,"consultedAt":5},
{"id":307,"patientID":19,"date":"12/15/2020","result":76,"consultedBy":1,"consultedAt":9},
{"id":308,"patientID":6,"date":"12/4/2020","result":81,"consultedBy":4,"consultedAt":7},
{"id":309,"patientID":65,"date":"12/22/2020","result":43,"consultedBy":2,"consultedAt":9},
{"id":310,"patientID":99,"date":"12/24/2020","result":69,"consultedBy":9,"consultedAt":2},
{"id":311,"patientID":29,"date":"12/29/2020","result":32,"consultedBy":5,"consultedAt":6},
{"id":312,"patientID":84,"date":"12/27/2020","result":10,"consultedBy":10,"consultedAt":1},
{"id":313,"patientID":32,"date":"12/5/2020","result":27,"consultedBy":8,"consultedAt":3},
{"id":314,"patientID":20,"date":"12/20/2020","result":17,"consultedBy":4,"consultedAt":3},
{"id":315,"patientID":100,"date":"12/5/2020","result":7,"consultedBy":4,"consultedAt":3},
{"id":316,"patientID":82,"date":"12/10/2020","result":1,"consultedBy":4,"consultedAt":6},
{"id":317,"patientID":40,"date":"12/26/2020","result":41,"consultedBy":6,"consultedAt":10},
{"id":318,"patientID":72,"date":"12/9/2020","result":74,"consultedBy":2,"consultedAt":7},
{"id":319,"patientID":92,"date":"12/17/2020","result":7,"consultedBy":4,"consultedAt":10},
{"id":320,"patientID":24,"date":"12/8/2020","result":29,"consultedBy":4,"consultedAt":5},
{"id":321,"patientID":58,"date":"12/28/2020","result":43,"consultedBy":4,"consultedAt":1},
{"id":322,"patientID":45,"date":"12/21/2020","result":22,"consultedBy":6,"consultedAt":7},
{"id":323,"patientID":56,"date":"12/9/2020","result":76,"consultedBy":6,"consultedAt":2},
{"id":324,"patientID":79,"date":"12/15/2020","result":62,"consultedBy":4,"consultedAt":5},
{"id":325,"patientID":66,"date":"12/22/2020","result":76,"consultedBy":3,"consultedAt":3},
{"id":326,"patientID":65,"date":"12/26/2020","result":97,"consultedBy":6,"consultedAt":8},
{"id":327,"patientID":64,"date":"12/18/2020","result":32,"consultedBy":6,"consultedAt":2},
{"id":328,"patientID":50,"date":"12/10/2020","result":100,"consultedBy":7,"consultedAt":9},
{"id":329,"patientID":23,"date":"12/15/2020","result":87,"consultedBy":7,"consultedAt":8},
{"id":330,"patientID":62,"date":"12/9/2020","result":38,"consultedBy":8,"consultedAt":3},
{"id":331,"patientID":66,"date":"12/23/2020","result":30,"consultedBy":9,"consultedAt":9},
{"id":332,"patientID":54,"date":"12/20/2020","result":17,"consultedBy":2,"consultedAt":4},
{"id":333,"patientID":24,"date":"12/9/2020","result":95,"consultedBy":8,"consultedAt":7},
{"id":334,"patientID":42,"date":"12/28/2020","result":5,"consultedBy":9,"consultedAt":7},
{"id":335,"patientID":50,"date":"12/5/2020","result":96,"consultedBy":5,"consultedAt":5},
{"id":336,"patientID":62,"date":"12/23/2020","result":18,"consultedBy":8,"consultedAt":7},
{"id":337,"patientID":93,"date":"12/13/2020","result":75,"consultedBy":6,"consultedAt":5},
{"id":338,"patientID":45,"date":"12/29/2020","result":60,"consultedBy":10,"consultedAt":7},
{"id":339,"patientID":81,"date":"1/2/2021","result":52,"consultedBy":2,"consultedAt":8},
{"id":340,"patientID":12,"date":"12/5/2020","result":17,"consultedBy":9,"consultedAt":4},
{"id":341,"patientID":35,"date":"12/8/2020","result":51,"consultedBy":5,"consultedAt":10},
{"id":342,"patientID":32,"date":"12/1/2020","result":7,"consultedBy":1,"consultedAt":7},
{"id":343,"patientID":99,"date":"12/27/2020","result":81,"consultedBy":10,"consultedAt":3},
{"id":344,"patientID":20,"date":"12/11/2020","result":87,"consultedBy":10,"consultedAt":4},
{"id":345,"patientID":40,"date":"12/8/2020","result":92,"consultedBy":7,"consultedAt":3},
{"id":346,"patientID":96,"date":"12/21/2020","result":20,"consultedBy":3,"consultedAt":10},
{"id":347,"patientID":9,"date":"12/16/2020","result":35,"consultedBy":6,"consultedAt":2},
{"id":348,"patientID":3,"date":"12/8/2020","result":30,"consultedBy":2,"consultedAt":5},
{"id":349,"patientID":67,"date":"12/19/2020","result":97,"consultedBy":5,"consultedAt":4},
{"id":350,"patientID":78,"date":"12/23/2020","result":5,"consultedBy":4,"consultedAt":10},
{"id":351,"patientID":5,"date":"12/26/2020","result":68,"consultedBy":3,"consultedAt":3},
{"id":352,"patientID":82,"date":"12/22/2020","result":13,"consultedBy":5,"consultedAt":2},
{"id":353,"patientID":63,"date":"12/3/2020","result":68,"consultedBy":2,"consultedAt":10},
{"id":354,"patientID":38,"date":"12/5/2020","result":87,"consultedBy":8,"consultedAt":4},
{"id":355,"patientID":10,"date":"12/18/2020","result":72,"consultedBy":5,"consultedAt":4},
{"id":356,"patientID":13,"date":"12/10/2020","result":85,"consultedBy":7,"consultedAt":1},
{"id":357,"patientID":52,"date":"12/9/2020","result":94,"consultedBy":3,"consultedAt":7},
{"id":358,"patientID":45,"date":"12/14/2020","result":38,"consultedBy":9,"consultedAt":9},
{"id":359,"patientID":23,"date":"12/11/2020","result":44,"consultedBy":10,"consultedAt":6},
{"id":360,"patientID":97,"date":"12/24/2020","result":46,"consultedBy":9,"consultedAt":5},
{"id":361,"patientID":59,"date":"12/14/2020","result":83,"consultedBy":6,"consultedAt":7},
{"id":362,"patientID":53,"date":"12/28/2020","result":8,"consultedBy":8,"consultedAt":4},
{"id":363,"patientID":87,"date":"12/27/2020","result":41,"consultedBy":8,"consultedAt":6},
{"id":364,"patientID":51,"date":"12/11/2020","result":91,"consultedBy":10,"consultedAt":4},
{"id":365,"patientID":88,"date":"12/12/2020","result":69,"consultedBy":7,"consultedAt":7},
{"id":366,"patientID":10,"date":"12/2/2020","result":37,"consultedBy":4,"consultedAt":9},
{"id":367,"patientID":24,"date":"12/14/2020","result":22,"consultedBy":10,"consultedAt":1},
{"id":368,"patientID":84,"date":"1/2/2021","result":100,"consultedBy":10,"consultedAt":5},
{"id":369,"patientID":15,"date":"12/17/2020","result":89,"consultedBy":4,"consultedAt":10},
{"id":370,"patientID":78,"date":"12/9/2020","result":17,"consultedBy":7,"consultedAt":6},
{"id":371,"patientID":16,"date":"12/18/2020","result":1,"consultedBy":4,"consultedAt":9},
{"id":372,"patientID":21,"date":"12/19/2020","result":24,"consultedBy":9,"consultedAt":3},
{"id":373,"patientID":4,"date":"12/14/2020","result":75,"consultedBy":8,"consultedAt":4},
{"id":374,"patientID":12,"date":"12/24/2020","result":61,"consultedBy":6,"consultedAt":9},
{"id":375,"patientID":74,"date":"12/23/2020","result":30,"consultedBy":7,"consultedAt":10},
{"id":376,"patientID":57,"date":"12/5/2020","result":84,"consultedBy":4,"consultedAt":3},
{"id":377,"patientID":75,"date":"12/20/2020","result":8,"consultedBy":7,"consultedAt":10},
{"id":378,"patientID":75,"date":"12/25/2020","result":78,"consultedBy":10,"consultedAt":3},
{"id":379,"patientID":48,"date":"12/11/2020","result":13,"consultedBy":7,"consultedAt":1},
{"id":380,"patientID":100,"date":"12/26/2020","result":99,"consultedBy":10,"consultedAt":8},
{"id":381,"patientID":78,"date":"12/22/2020","result":3,"consultedBy":3,"consultedAt":9},
{"id":382,"patientID":42,"date":"12/23/2020","result":96,"consultedBy":1,"consultedAt":2},
{"id":383,"patientID":82,"date":"12/16/2020","result":47,"consultedBy":9,"consultedAt":4},
{"id":384,"patientID":32,"date":"12/20/2020","result":42,"consultedBy":5,"consultedAt":10},
{"id":385,"patientID":22,"date":"12/21/2020","result":28,"consultedBy":10,"consultedAt":1},
{"id":386,"patientID":43,"date":"1/1/2021","result":18,"consultedBy":2,"consultedAt":5},
{"id":387,"patientID":25,"date":"1/1/2021","result":55,"consultedBy":9,"consultedAt":2},
{"id":388,"patientID":97,"date":"12/22/2020","result":68,"consultedBy":8,"consultedAt":10},
{"id":389,"patientID":82,"date":"1/1/2021","result":62,"consultedBy":1,"consultedAt":8},
{"id":390,"patientID":15,"date":"12/8/2020","result":61,"consultedBy":4,"consultedAt":5},
{"id":391,"patientID":54,"date":"12/14/2020","result":35,"consultedBy":3,"consultedAt":4},
{"id":392,"patientID":1,"date":"12/9/2020","result":70,"consultedBy":2,"consultedAt":7},
{"id":393,"patientID":20,"date":"12/30/2020","result":2,"consultedBy":2,"consultedAt":7},
{"id":394,"patientID":84,"date":"12/30/2020","result":96,"consultedBy":1,"consultedAt":6},
{"id":395,"patientID":8,"date":"12/2/2020","result":77,"consultedBy":1,"consultedAt":3},
{"id":396,"patientID":78,"date":"12/14/2020","result":42,"consultedBy":4,"consultedAt":9},
{"id":397,"patientID":78,"date":"12/13/2020","result":70,"consultedBy":7,"consultedAt":10},
{"id":398,"patientID":42,"date":"12/10/2020","result":78,"consultedBy":1,"consultedAt":8},
{"id":399,"patientID":82,"date":"12/21/2020","result":67,"consultedBy":2,"consultedAt":9},
{"id":400,"patientID":5,"date":"12/15/2020","result":73,"consultedBy":6,"consultedAt":7},
{"id":401,"patientID":14,"date":"12/9/2020","result":65,"consultedBy":7,"consultedAt":8},
{"id":402,"patientID":86,"date":"12/14/2020","result":13,"consultedBy":6,"consultedAt":7},
{"id":403,"patientID":77,"date":"12/22/2020","result":59,"consultedBy":8,"consultedAt":6},
{"id":404,"patientID":16,"date":"12/24/2020","result":88,"consultedBy":8,"consultedAt":1},
{"id":405,"patientID":61,"date":"12/31/2020","result":91,"consultedBy":9,"consultedAt":1},
{"id":406,"patientID":2,"date":"12/29/2020","result":63,"consultedBy":3,"consultedAt":3},
{"id":407,"patientID":31,"date":"12/16/2020","result":92,"consultedBy":5,"consultedAt":4},
{"id":408,"patientID":21,"date":"12/31/2020","result":39,"consultedBy":9,"consultedAt":3},
{"id":409,"patientID":24,"date":"12/8/2020","result":42,"consultedBy":9,"consultedAt":7},
{"id":410,"patientID":54,"date":"12/24/2020","result":26,"consultedBy":9,"consultedAt":6},
{"id":411,"patientID":39,"date":"12/9/2020","result":32,"consultedBy":5,"consultedAt":8},
{"id":412,"patientID":92,"date":"12/18/2020","result":8,"consultedBy":10,"consultedAt":5},
{"id":413,"patientID":38,"date":"12/4/2020","result":63,"consultedBy":10,"consultedAt":2},
{"id":414,"patientID":34,"date":"1/2/2021","result":13,"consultedBy":10,"consultedAt":1},
{"id":415,"patientID":28,"date":"12/23/2020","result":100,"consultedBy":2,"consultedAt":2},
{"id":416,"patientID":97,"date":"12/13/2020","result":97,"consultedBy":3,"consultedAt":3},
{"id":417,"patientID":67,"date":"12/4/2020","result":84,"consultedBy":6,"consultedAt":6},
{"id":418,"patientID":23,"date":"12/6/2020","result":72,"consultedBy":5,"consultedAt":3},
{"id":419,"patientID":58,"date":"12/11/2020","result":16,"consultedBy":5,"consultedAt":9},
{"id":420,"patientID":42,"date":"12/10/2020","result":81,"consultedBy":4,"consultedAt":1},
{"id":421,"patientID":64,"date":"12/27/2020","result":59,"consultedBy":4,"consultedAt":4},
{"id":422,"patientID":82,"date":"12/29/2020","result":86,"consultedBy":2,"consultedAt":1},
{"id":423,"patientID":39,"date":"12/20/2020","result":86,"consultedBy":3,"consultedAt":7},
{"id":424,"patientID":92,"date":"12/25/2020","result":33,"consultedBy":7,"consultedAt":7},
{"id":425,"patientID":10,"date":"12/6/2020","result":41,"consultedBy":9,"consultedAt":8},
{"id":426,"patientID":77,"date":"12/31/2020","result":40,"consultedBy":3,"consultedAt":5},
{"id":427,"patientID":66,"date":"12/2/2020","result":25,"consultedBy":9,"consultedAt":8},
{"id":428,"patientID":39,"date":"12/17/2020","result":41,"consultedBy":6,"consultedAt":7},
{"id":429,"patientID":11,"date":"12/21/2020","result":86,"consultedBy":4,"consultedAt":4},
{"id":430,"patientID":80,"date":"12/15/2020","result":12,"consultedBy":4,"consultedAt":6},
{"id":431,"patientID":40,"date":"12/4/2020","result":41,"consultedBy":4,"consultedAt":10},
{"id":432,"patientID":63,"date":"12/2/2020","result":93,"consultedBy":5,"consultedAt":6},
{"id":433,"patientID":1,"date":"12/11/2020","result":44,"consultedBy":2,"consultedAt":6},
{"id":434,"patientID":71,"date":"12/31/2020","result":79,"consultedBy":3,"consultedAt":1},
{"id":435,"patientID":52,"date":"12/8/2020","result":35,"consultedBy":7,"consultedAt":4},
{"id":436,"patientID":5,"date":"12/10/2020","result":37,"consultedBy":3,"consultedAt":1},
{"id":437,"patientID":68,"date":"12/24/2020","result":41,"consultedBy":9,"consultedAt":3},
{"id":438,"patientID":68,"date":"12/25/2020","result":39,"consultedBy":2,"consultedAt":9},
{"id":439,"patientID":37,"date":"12/13/2020","result":98,"consultedBy":1,"consultedAt":5},
{"id":440,"patientID":24,"date":"12/23/2020","result":14,"consultedBy":8,"consultedAt":6},
{"id":441,"patientID":92,"date":"12/15/2020","result":64,"consultedBy":3,"consultedAt":5},
{"id":442,"patientID":29,"date":"12/11/2020","result":58,"consultedBy":4,"consultedAt":8},
{"id":443,"patientID":87,"date":"12/8/2020","result":12,"consultedBy":4,"consultedAt":1},
{"id":444,"patientID":78,"date":"12/19/2020","result":52,"consultedBy":7,"consultedAt":10},
{"id":445,"patientID":22,"date":"12/25/2020","result":95,"consultedBy":3,"consultedAt":8},
{"id":446,"patientID":75,"date":"12/2/2020","result":13,"consultedBy":7,"consultedAt":2},
{"id":447,"patientID":14,"date":"12/24/2020","result":12,"consultedBy":6,"consultedAt":1},
{"id":448,"patientID":70,"date":"12/9/2020","result":61,"consultedBy":6,"consultedAt":1},
{"id":449,"patientID":92,"date":"12/1/2020","result":25,"consultedBy":2,"consultedAt":5},
{"id":450,"patientID":16,"date":"12/23/2020","result":98,"consultedBy":6,"consultedAt":5},
{"id":451,"patientID":54,"date":"12/2/2020","result":49,"consultedBy":5,"consultedAt":2},
{"id":452,"patientID":100,"date":"12/27/2020","result":12,"consultedBy":3,"consultedAt":2},
{"id":453,"patientID":26,"date":"12/2/2020","result":46,"consultedBy":3,"consultedAt":6},
{"id":454,"patientID":71,"date":"12/24/2020","result":10,"consultedBy":4,"consultedAt":3},
{"id":455,"patientID":64,"date":"12/13/2020","result":73,"consultedBy":2,"consultedAt":9},
{"id":456,"patientID":10,"date":"12/17/2020","result":70,"consultedBy":10,"consultedAt":10},
{"id":457,"patientID":55,"date":"12/10/2020","result":68,"consultedBy":5,"consultedAt":4},
{"id":458,"patientID":74,"date":"12/11/2020","result":28,"consultedBy":9,"consultedAt":1},
{"id":459,"patientID":100,"date":"12/17/2020","result":65,"consultedBy":5,"consultedAt":5},
{"id":460,"patientID":10,"date":"1/1/2021","result":89,"consultedBy":3,"consultedAt":10},
{"id":461,"patientID":34,"date":"12/28/2020","result":76,"consultedBy":3,"consultedAt":3},
{"id":462,"patientID":38,"date":"12/11/2020","result":74,"consultedBy":9,"consultedAt":9},
{"id":463,"patientID":30,"date":"12/26/2020","result":77,"consultedBy":3,"consultedAt":8},
{"id":464,"patientID":28,"date":"12/25/2020","result":68,"consultedBy":3,"consultedAt":8},
{"id":465,"patientID":60,"date":"12/22/2020","result":35,"consultedBy":4,"consultedAt":2},
{"id":466,"patientID":68,"date":"12/5/2020","result":15,"consultedBy":8,"consultedAt":7},
{"id":467,"patientID":37,"date":"12/12/2020","result":85,"consultedBy":8,"consultedAt":5},
{"id":468,"patientID":96,"date":"12/6/2020","result":35,"consultedBy":1,"consultedAt":8},
{"id":469,"patientID":70,"date":"12/3/2020","result":24,"consultedBy":2,"consultedAt":2},
{"id":470,"patientID":75,"date":"12/8/2020","result":31,"consultedBy":2,"consultedAt":2},
{"id":471,"patientID":75,"date":"12/17/2020","result":73,"consultedBy":1,"consultedAt":7},
{"id":472,"patientID":98,"date":"12/27/2020","result":65,"consultedBy":3,"consultedAt":6},
{"id":473,"patientID":38,"date":"12/21/2020","result":28,"consultedBy":10,"consultedAt":1},
{"id":474,"patientID":22,"date":"12/15/2020","result":91,"consultedBy":1,"consultedAt":9},
{"id":475,"patientID":19,"date":"12/23/2020","result":22,"consultedBy":2,"consultedAt":10},
{"id":476,"patientID":96,"date":"12/15/2020","result":85,"consultedBy":4,"consultedAt":5},
{"id":477,"patientID":17,"date":"12/24/2020","result":30,"consultedBy":2,"consultedAt":10},
{"id":478,"patientID":45,"date":"12/15/2020","result":55,"consultedBy":1,"consultedAt":5},
{"id":479,"patientID":88,"date":"12/26/2020","result":8,"consultedBy":9,"consultedAt":8},
{"id":480,"patientID":53,"date":"12/20/2020","result":28,"consultedBy":8,"consultedAt":10},
{"id":481,"patientID":5,"date":"12/28/2020","result":70,"consultedBy":7,"consultedAt":10},
{"id":482,"patientID":41,"date":"12/21/2020","result":34,"consultedBy":6,"consultedAt":1},
{"id":483,"patientID":33,"date":"12/5/2020","result":51,"consultedBy":10,"consultedAt":1},
{"id":484,"patientID":33,"date":"12/29/2020","result":32,"consultedBy":3,"consultedAt":2},
{"id":485,"patientID":16,"date":"12/10/2020","result":51,"consultedBy":9,"consultedAt":5},
{"id":486,"patientID":80,"date":"12/16/2020","result":26,"consultedBy":3,"consultedAt":10},
{"id":487,"patientID":85,"date":"12/13/2020","result":87,"consultedBy":4,"consultedAt":6},
{"id":488,"patientID":88,"date":"12/27/2020","result":32,"consultedBy":1,"consultedAt":7},
{"id":489,"patientID":59,"date":"12/19/2020","result":51,"consultedBy":3,"consultedAt":7},
{"id":490,"patientID":95,"date":"1/2/2021","result":10,"consultedBy":8,"consultedAt":1},
{"id":491,"patientID":57,"date":"12/24/2020","result":5,"consultedBy":6,"consultedAt":3},
{"id":492,"patientID":30,"date":"12/12/2020","result":100,"consultedBy":1,"consultedAt":7},
{"id":493,"patientID":71,"date":"12/23/2020","result":16,"consultedBy":4,"consultedAt":1},
{"id":494,"patientID":54,"date":"12/28/2020","result":70,"consultedBy":6,"consultedAt":2},
{"id":495,"patientID":98,"date":"12/23/2020","result":75,"consultedBy":5,"consultedAt":9},
{"id":496,"patientID":23,"date":"12/24/2020","result":54,"consultedBy":2,"consultedAt":10},
{"id":497,"patientID":8,"date":"12/30/2020","result":35,"consultedBy":1,"consultedAt":7},
{"id":498,"patientID":32,"date":"12/1/2020","result":67,"consultedBy":9,"consultedAt":9},
{"id":499,"patientID":3,"date":"12/8/2020","result":21,"consultedBy":10,"consultedAt":10},
{"id":500,"patientID":64,"date":"12/18/2020","result":39,"consultedBy":4,"consultedAt":9},
{"id":501,"patientID":21,"date":"12/17/2020","result":97,"consultedBy":1,"consultedAt":10},
{"id":502,"patientID":58,"date":"12/1/2020","result":86,"consultedBy":2,"consultedAt":3},
{"id":503,"patientID":37,"date":"12/8/2020","result":67,"consultedBy":9,"consultedAt":8},
{"id":504,"patientID":57,"date":"12/19/2020","result":70,"consultedBy":8,"consultedAt":5},
{"id":505,"patientID":26,"date":"12/27/2020","result":16,"consultedBy":7,"consultedAt":9},
{"id":506,"patientID":53,"date":"12/11/2020","result":38,"consultedBy":8,"consultedAt":4},
{"id":507,"patientID":7,"date":"12/15/2020","result":16,"consultedBy":8,"consultedAt":3},
{"id":508,"patientID":88,"date":"1/2/2021","result":13,"consultedBy":1,"consultedAt":7},
{"id":509,"patientID":43,"date":"1/1/2021","result":90,"consultedBy":1,"consultedAt":3},
{"id":510,"patientID":73,"date":"12/13/2020","result":55,"consultedBy":4,"consultedAt":4},
{"id":511,"patientID":98,"date":"12/29/2020","result":1,"consultedBy":8,"consultedAt":10},
{"id":512,"patientID":37,"date":"12/29/2020","result":55,"consultedBy":2,"consultedAt":7},
{"id":513,"patientID":98,"date":"12/31/2020","result":40,"consultedBy":7,"consultedAt":2},
{"id":514,"patientID":93,"date":"12/2/2020","result":2,"consultedBy":8,"consultedAt":10},
{"id":515,"patientID":96,"date":"12/14/2020","result":85,"consultedBy":1,"consultedAt":6},
{"id":516,"patientID":43,"date":"12/19/2020","result":73,"consultedBy":9,"consultedAt":1},
{"id":517,"patientID":100,"date":"12/7/2020","result":54,"consultedBy":6,"consultedAt":9},
{"id":518,"patientID":26,"date":"12/12/2020","result":97,"consultedBy":2,"consultedAt":3},
{"id":519,"patientID":80,"date":"12/18/2020","result":58,"consultedBy":6,"consultedAt":4},
{"id":520,"patientID":80,"date":"12/19/2020","result":98,"consultedBy":6,"consultedAt":7},
{"id":521,"patientID":99,"date":"12/1/2020","result":93,"consultedBy":1,"consultedAt":2},
{"id":522,"patientID":55,"date":"12/24/2020","result":16,"consultedBy":5,"consultedAt":7},
{"id":523,"patientID":62,"date":"12/18/2020","result":6,"consultedBy":9,"consultedAt":9},
{"id":524,"patientID":6,"date":"12/15/2020","result":47,"consultedBy":6,"consultedAt":5},
{"id":525,"patientID":72,"date":"1/1/2021","result":59,"consultedBy":9,"consultedAt":8},
{"id":526,"patientID":81,"date":"12/26/2020","result":89,"consultedBy":6,"consultedAt":10},
{"id":527,"patientID":28,"date":"12/17/2020","result":55,"consultedBy":3,"consultedAt":6},
{"id":528,"patientID":78,"date":"12/6/2020","result":36,"consultedBy":9,"consultedAt":2},
{"id":529,"patientID":57,"date":"12/18/2020","result":53,"consultedBy":10,"consultedAt":8},
{"id":530,"patientID":33,"date":"12/8/2020","result":83,"consultedBy":3,"consultedAt":4},
{"id":531,"patientID":39,"date":"12/16/2020","result":11,"consultedBy":5,"consultedAt":5},
{"id":532,"patientID":76,"date":"12/30/2020","result":78,"consultedBy":4,"consultedAt":4},
{"id":533,"patientID":76,"date":"12/2/2020","result":26,"consultedBy":10,"consultedAt":1},
{"id":534,"patientID":42,"date":"12/14/2020","result":19,"consultedBy":4,"consultedAt":8},
{"id":535,"patientID":92,"date":"1/1/2021","result":72,"consultedBy":1,"consultedAt":2},
{"id":536,"patientID":56,"date":"12/5/2020","result":78,"consultedBy":5,"consultedAt":5},
{"id":537,"patientID":34,"date":"12/11/2020","result":19,"consultedBy":4,"consultedAt":9},
{"id":538,"patientID":55,"date":"12/1/2020","result":6,"consultedBy":8,"consultedAt":8},
{"id":539,"patientID":84,"date":"1/2/2021","result":91,"consultedBy":1,"consultedAt":6},
{"id":540,"patientID":27,"date":"12/16/2020","result":24,"consultedBy":6,"consultedAt":6},
{"id":541,"patientID":95,"date":"12/25/2020","result":57,"consultedBy":5,"consultedAt":1},
{"id":542,"patientID":75,"date":"1/1/2021","result":84,"consultedBy":2,"consultedAt":3},
{"id":543,"patientID":19,"date":"1/1/2021","result":52,"consultedBy":8,"consultedAt":6},
{"id":544,"patientID":19,"date":"12/20/2020","result":56,"consultedBy":5,"consultedAt":7},
{"id":545,"patientID":66,"date":"12/15/2020","result":80,"consultedBy":4,"consultedAt":8},
{"id":546,"patientID":10,"date":"12/31/2020","result":38,"consultedBy":8,"consultedAt":2},
{"id":547,"patientID":100,"date":"12/13/2020","result":34,"consultedBy":7,"consultedAt":1},
{"id":548,"patientID":83,"date":"12/25/2020","result":13,"consultedBy":6,"consultedAt":10},
{"id":549,"patientID":49,"date":"12/8/2020","result":74,"consultedBy":8,"consultedAt":10},
{"id":550,"patientID":92,"date":"12/24/2020","result":21,"consultedBy":4,"consultedAt":5},
{"id":551,"patientID":76,"date":"12/9/2020","result":72,"consultedBy":10,"consultedAt":8},
{"id":552,"patientID":68,"date":"12/8/2020","result":12,"consultedBy":10,"consultedAt":5},
{"id":553,"patientID":99,"date":"12/2/2020","result":52,"consultedBy":2,"consultedAt":1},
{"id":554,"patientID":92,"date":"12/3/2020","result":30,"consultedBy":3,"consultedAt":7},
{"id":555,"patientID":55,"date":"12/1/2020","result":55,"consultedBy":9,"consultedAt":6},
{"id":556,"patientID":68,"date":"12/18/2020","result":52,"consultedBy":8,"consultedAt":8},
{"id":557,"patientID":51,"date":"12/3/2020","result":15,"consultedBy":5,"consultedAt":4},
{"id":558,"patientID":59,"date":"12/12/2020","result":21,"consultedBy":9,"consultedAt":7},
{"id":559,"patientID":87,"date":"12/13/2020","result":68,"consultedBy":1,"consultedAt":3},
{"id":560,"patientID":98,"date":"12/16/2020","result":52,"consultedBy":9,"consultedAt":8},
{"id":561,"patientID":53,"date":"12/2/2020","result":98,"consultedBy":1,"consultedAt":8},
{"id":562,"patientID":88,"date":"12/20/2020","result":56,"consultedBy":1,"consultedAt":8},
{"id":563,"patientID":94,"date":"12/18/2020","result":77,"consultedBy":2,"consultedAt":5},
{"id":564,"patientID":39,"date":"12/9/2020","result":81,"consultedBy":7,"consultedAt":5},
{"id":565,"patientID":99,"date":"12/7/2020","result":23,"consultedBy":3,"consultedAt":1},
{"id":566,"patientID":96,"date":"12/2/2020","result":63,"consultedBy":1,"consultedAt":6},
{"id":567,"patientID":31,"date":"12/18/2020","result":86,"consultedBy":2,"consultedAt":9},
{"id":568,"patientID":31,"date":"12/16/2020","result":86,"consultedBy":5,"consultedAt":10},
{"id":569,"patientID":54,"date":"12/13/2020","result":53,"consultedBy":6,"consultedAt":5},
{"id":570,"patientID":4,"date":"12/2/2020","result":27,"consultedBy":5,"consultedAt":8},
{"id":571,"patientID":50,"date":"12/30/2020","result":24,"consultedBy":7,"consultedAt":2},
{"id":572,"patientID":49,"date":"1/1/2021","result":77,"consultedBy":10,"consultedAt":1},
{"id":573,"patientID":68,"date":"12/4/2020","result":28,"consultedBy":2,"consultedAt":2},
{"id":574,"patientID":22,"date":"12/6/2020","result":88,"consultedBy":8,"consultedAt":8},
{"id":575,"patientID":39,"date":"12/21/2020","result":12,"consultedBy":6,"consultedAt":2},
{"id":576,"patientID":33,"date":"12/14/2020","result":2,"consultedBy":1,"consultedAt":8},
{"id":577,"patientID":53,"date":"12/21/2020","result":73,"consultedBy":5,"consultedAt":3},
{"id":578,"patientID":10,"date":"12/20/2020","result":63,"consultedBy":4,"consultedAt":9},
{"id":579,"patientID":4,"date":"12/6/2020","result":5,"consultedBy":9,"consultedAt":9},
{"id":580,"patientID":8,"date":"12/20/2020","result":54,"consultedBy":10,"consultedAt":10},
{"id":581,"patientID":83,"date":"12/27/2020","result":31,"consultedBy":10,"consultedAt":6},
{"id":582,"patientID":12,"date":"12/8/2020","result":83,"consultedBy":2,"consultedAt":1},
{"id":583,"patientID":74,"date":"12/5/2020","result":69,"consultedBy":5,"consultedAt":4},
{"id":584,"patientID":89,"date":"12/8/2020","result":79,"consultedBy":6,"consultedAt":8},
{"id":585,"patientID":83,"date":"12/30/2020","result":36,"consultedBy":7,"consultedAt":4},
{"id":586,"patientID":51,"date":"1/1/2021","result":82,"consultedBy":4,"consultedAt":1},
{"id":587,"patientID":46,"date":"12/29/2020","result":18,"consultedBy":1,"consultedAt":6},
{"id":588,"patientID":32,"date":"12/3/2020","result":65,"consultedBy":5,"consultedAt":1},
{"id":589,"patientID":62,"date":"12/27/2020","result":71,"consultedBy":1,"consultedAt":5},
{"id":590,"patientID":22,"date":"12/15/2020","result":59,"consultedBy":8,"consultedAt":7},
{"id":591,"patientID":14,"date":"12/3/2020","result":18,"consultedBy":7,"consultedAt":7},
{"id":592,"patientID":36,"date":"12/12/2020","result":12,"consultedBy":7,"consultedAt":7},
{"id":593,"patientID":69,"date":"12/16/2020","result":65,"consultedBy":1,"consultedAt":6},
{"id":594,"patientID":63,"date":"12/3/2020","result":58,"consultedBy":8,"consultedAt":8},
{"id":595,"patientID":6,"date":"12/31/2020","result":88,"consultedBy":8,"consultedAt":8},
{"id":596,"patientID":9,"date":"12/3/2020","result":46,"consultedBy":2,"consultedAt":10},
{"id":597,"patientID":54,"date":"12/14/2020","result":18,"consultedBy":10,"consultedAt":10},
{"id":598,"patientID":11,"date":"12/7/2020","result":52,"consultedBy":5,"consultedAt":10},
{"id":599,"patientID":3,"date":"12/11/2020","result":33,"consultedBy":7,"consultedAt":3},
{"id":600,"patientID":68,"date":"12/13/2020","result":26,"consultedBy":9,"consultedAt":10},
{"id":601,"patientID":18,"date":"12/15/2020","result":40,"consultedBy":6,"consultedAt":1},
{"id":602,"patientID":45,"date":"12/19/2020","result":80,"consultedBy":4,"consultedAt":2},
{"id":603,"patientID":64,"date":"12/9/2020","result":81,"consultedBy":4,"consultedAt":4},
{"id":604,"patientID":54,"date":"12/28/2020","result":80,"consultedBy":2,"consultedAt":6},
{"id":605,"patientID":84,"date":"12/24/2020","result":61,"consultedBy":8,"consultedAt":9},
{"id":606,"patientID":71,"date":"12/11/2020","result":29,"consultedBy":2,"consultedAt":3},
{"id":607,"patientID":43,"date":"1/2/2021","result":34,"consultedBy":3,"consultedAt":5},
{"id":608,"patientID":66,"date":"1/2/2021","result":14,"consultedBy":10,"consultedAt":10},
{"id":609,"patientID":36,"date":"12/3/2020","result":41,"consultedBy":1,"consultedAt":6},
{"id":610,"patientID":9,"date":"12/14/2020","result":62,"consultedBy":9,"consultedAt":5},
{"id":611,"patientID":76,"date":"1/2/2021","result":50,"consultedBy":2,"consultedAt":7},
{"id":612,"patientID":28,"date":"12/14/2020","result":95,"consultedBy":1,"consultedAt":7},
{"id":613,"patientID":62,"date":"12/24/2020","result":92,"consultedBy":6,"consultedAt":3},
{"id":614,"patientID":16,"date":"1/1/2021","result":52,"consultedBy":6,"consultedAt":10},
{"id":615,"patientID":5,"date":"12/15/2020","result":43,"consultedBy":9,"consultedAt":9},
{"id":616,"patientID":85,"date":"12/20/2020","result":45,"consultedBy":5,"consultedAt":4},
{"id":617,"patientID":59,"date":"12/13/2020","result":86,"consultedBy":2,"consultedAt":3},
{"id":618,"patientID":20,"date":"12/7/2020","result":64,"consultedBy":2,"consultedAt":4},
{"id":619,"patientID":14,"date":"12/17/2020","result":48,"consultedBy":3,"consultedAt":10},
{"id":620,"patientID":82,"date":"12/24/2020","result":29,"consultedBy":6,"consultedAt":3},
{"id":621,"patientID":17,"date":"12/6/2020","result":2,"consultedBy":5,"consultedAt":5},
{"id":622,"patientID":48,"date":"12/3/2020","result":57,"consultedBy":10,"consultedAt":6},
{"id":623,"patientID":96,"date":"12/7/2020","result":17,"consultedBy":8,"consultedAt":7},
{"id":624,"patientID":14,"date":"12/28/2020","result":18,"consultedBy":5,"consultedAt":10},
{"id":625,"patientID":33,"date":"12/23/2020","result":99,"consultedBy":4,"consultedAt":2},
{"id":626,"patientID":29,"date":"12/21/2020","result":81,"consultedBy":6,"consultedAt":3},
{"id":627,"patientID":20,"date":"1/2/2021","result":62,"consultedBy":10,"consultedAt":1},
{"id":628,"patientID":52,"date":"12/8/2020","result":83,"consultedBy":10,"consultedAt":10},
{"id":629,"patientID":100,"date":"12/13/2020","result":52,"consultedBy":2,"consultedAt":2},
{"id":630,"patientID":9,"date":"12/17/2020","result":9,"consultedBy":5,"consultedAt":7},
{"id":631,"patientID":2,"date":"12/16/2020","result":41,"consultedBy":4,"consultedAt":7},
{"id":632,"patientID":50,"date":"12/2/2020","result":23,"consultedBy":10,"consultedAt":2},
{"id":633,"patientID":23,"date":"12/29/2020","result":97,"consultedBy":6,"consultedAt":5},
{"id":634,"patientID":78,"date":"12/10/2020","result":48,"consultedBy":6,"consultedAt":6},
{"id":635,"patientID":50,"date":"12/29/2020","result":77,"consultedBy":4,"consultedAt":1},
{"id":636,"patientID":28,"date":"12/21/2020","result":28,"consultedBy":2,"consultedAt":1},
{"id":637,"patientID":54,"date":"12/30/2020","result":62,"consultedBy":1,"consultedAt":6},
{"id":638,"patientID":34,"date":"12/13/2020","result":100,"consultedBy":9,"consultedAt":7},
{"id":639,"patientID":9,"date":"12/14/2020","result":27,"consultedBy":10,"consultedAt":1},
{"id":640,"patientID":25,"date":"12/7/2020","result":81,"consultedBy":5,"consultedAt":1},
{"id":641,"patientID":28,"date":"12/23/2020","result":95,"consultedBy":9,"consultedAt":3},
{"id":642,"patientID":48,"date":"12/1/2020","result":41,"consultedBy":2,"consultedAt":7},
{"id":643,"patientID":18,"date":"12/21/2020","result":28,"consultedBy":8,"consultedAt":1},
{"id":644,"patientID":92,"date":"12/23/2020","result":99,"consultedBy":8,"consultedAt":4},
{"id":645,"patientID":3,"date":"12/14/2020","result":63,"consultedBy":6,"consultedAt":9},
{"id":646,"patientID":94,"date":"1/2/2021","result":46,"consultedBy":4,"consultedAt":10},
{"id":647,"patientID":30,"date":"1/1/2021","result":35,"consultedBy":4,"consultedAt":8},
{"id":648,"patientID":31,"date":"12/17/2020","result":21,"consultedBy":3,"consultedAt":3},
{"id":649,"patientID":47,"date":"12/4/2020","result":95,"consultedBy":9,"consultedAt":2},
{"id":650,"patientID":78,"date":"12/13/2020","result":53,"consultedBy":10,"consultedAt":4},
{"id":651,"patientID":27,"date":"12/5/2020","result":17,"consultedBy":2,"consultedAt":8},
{"id":652,"patientID":82,"date":"12/31/2020","result":5,"consultedBy":2,"consultedAt":9},
{"id":653,"patientID":91,"date":"1/2/2021","result":97,"consultedBy":7,"consultedAt":10},
{"id":654,"patientID":65,"date":"12/30/2020","result":70,"consultedBy":6,"consultedAt":8},
{"id":655,"patientID":52,"date":"12/11/2020","result":39,"consultedBy":10,"consultedAt":5},
{"id":656,"patientID":5,"date":"12/18/2020","result":1,"consultedBy":1,"consultedAt":9},
{"id":657,"patientID":70,"date":"12/8/2020","result":38,"consultedBy":3,"consultedAt":2},
{"id":658,"patientID":24,"date":"12/5/2020","result":94,"consultedBy":9,"consultedAt":4},
{"id":659,"patientID":54,"date":"12/7/2020","result":11,"consultedBy":6,"consultedAt":8},
{"id":660,"patientID":41,"date":"12/28/2020","result":9,"consultedBy":5,"consultedAt":6},
{"id":661,"patientID":35,"date":"12/30/2020","result":81,"consultedBy":7,"consultedAt":3},
{"id":662,"patientID":46,"date":"12/19/2020","result":16,"consultedBy":4,"consultedAt":5},
{"id":663,"patientID":29,"date":"12/10/2020","result":92,"consultedBy":6,"consultedAt":2},
{"id":664,"patientID":6,"date":"12/28/2020","result":6,"consultedBy":9,"consultedAt":1},
{"id":665,"patientID":40,"date":"12/23/2020","result":38,"consultedBy":10,"consultedAt":6},
{"id":666,"patientID":66,"date":"12/14/2020","result":40,"consultedBy":9,"consultedAt":7},
{"id":667,"patientID":46,"date":"12/11/2020","result":68,"consultedBy":10,"consultedAt":2},
{"id":668,"patientID":2,"date":"12/8/2020","result":22,"consultedBy":2,"consultedAt":9},
{"id":669,"patientID":24,"date":"12/29/2020","result":44,"consultedBy":3,"consultedAt":10},
{"id":670,"patientID":96,"date":"12/11/2020","result":36,"consultedBy":1,"consultedAt":4},
{"id":671,"patientID":32,"date":"12/25/2020","result":43,"consultedBy":10,"consultedAt":5},
{"id":672,"patientID":44,"date":"12/9/2020","result":43,"consultedBy":7,"consultedAt":1},
{"id":673,"patientID":70,"date":"12/12/2020","result":10,"consultedBy":2,"consultedAt":1},
{"id":674,"patientID":29,"date":"12/7/2020","result":63,"consultedBy":9,"consultedAt":2},
{"id":675,"patientID":45,"date":"12/27/2020","result":39,"consultedBy":4,"consultedAt":10},
{"id":676,"patientID":97,"date":"12/16/2020","result":32,"consultedBy":10,"consultedAt":9},
{"id":677,"patientID":73,"date":"12/17/2020","result":3,"consultedBy":6,"consultedAt":7},
{"id":678,"patientID":65,"date":"12/31/2020","result":20,"consultedBy":7,"consultedAt":4},
{"id":679,"patientID":77,"date":"12/1/2020","result":18,"consultedBy":3,"consultedAt":6},
{"id":680,"patientID":99,"date":"12/8/2020","result":15,"consultedBy":9,"consultedAt":4},
{"id":681,"patientID":58,"date":"12/12/2020","result":37,"consultedBy":6,"consultedAt":10},
{"id":682,"patientID":76,"date":"12/1/2020","result":35,"consultedBy":4,"consultedAt":6},
{"id":683,"patientID":3,"date":"12/13/2020","result":1,"consultedBy":1,"consultedAt":6},
{"id":684,"patientID":51,"date":"1/1/2021","result":95,"consultedBy":3,"consultedAt":4},
{"id":685,"patientID":51,"date":"12/14/2020","result":58,"consultedBy":10,"consultedAt":9},
{"id":686,"patientID":92,"date":"12/12/2020","result":87,"consultedBy":4,"consultedAt":3},
{"id":687,"patientID":18,"date":"12/21/2020","result":70,"consultedBy":4,"consultedAt":3},
{"id":688,"patientID":93,"date":"12/21/2020","result":11,"consultedBy":4,"consultedAt":9},
{"id":689,"patientID":18,"date":"12/4/2020","result":90,"consultedBy":9,"consultedAt":8},
{"id":690,"patientID":45,"date":"12/8/2020","result":63,"consultedBy":2,"consultedAt":4},
{"id":691,"patientID":58,"date":"12/30/2020","result":77,"consultedBy":2,"consultedAt":10},
{"id":692,"patientID":93,"date":"12/5/2020","result":6,"consultedBy":4,"consultedAt":8},
{"id":693,"patientID":55,"date":"12/16/2020","result":45,"consultedBy":1,"consultedAt":1},
{"id":694,"patientID":58,"date":"1/2/2021","result":76,"consultedBy":3,"consultedAt":9},
{"id":695,"patientID":42,"date":"12/8/2020","result":16,"consultedBy":5,"consultedAt":6},
{"id":696,"patientID":92,"date":"12/26/2020","result":87,"consultedBy":4,"consultedAt":1},
{"id":697,"patientID":57,"date":"12/6/2020","result":56,"consultedBy":9,"consultedAt":2},
{"id":698,"patientID":97,"date":"12/22/2020","result":92,"consultedBy":8,"consultedAt":1},
{"id":699,"patientID":83,"date":"12/8/2020","result":32,"consultedBy":7,"consultedAt":5},
{"id":700,"patientID":72,"date":"12/26/2020","result":27,"consultedBy":8,"consultedAt":6},
{"id":701,"patientID":68,"date":"12/17/2020","result":44,"consultedBy":3,"consultedAt":10},
{"id":702,"patientID":46,"date":"12/20/2020","result":42,"consultedBy":10,"consultedAt":4},
{"id":703,"patientID":26,"date":"12/8/2020","result":81,"consultedBy":3,"consultedAt":2},
{"id":704,"patientID":91,"date":"12/10/2020","result":55,"consultedBy":1,"consultedAt":3},
{"id":705,"patientID":22,"date":"12/18/2020","result":99,"consultedBy":2,"consultedAt":1},
{"id":706,"patientID":95,"date":"12/16/2020","result":85,"consultedBy":9,"consultedAt":1},
{"id":707,"patientID":81,"date":"12/8/2020","result":42,"consultedBy":9,"consultedAt":2},
{"id":708,"patientID":95,"date":"12/5/2020","result":30,"consultedBy":1,"consultedAt":1},
{"id":709,"patientID":52,"date":"12/10/2020","result":61,"consultedBy":7,"consultedAt":3},
{"id":710,"patientID":69,"date":"12/9/2020","result":25,"consultedBy":9,"consultedAt":1},
{"id":711,"patientID":16,"date":"12/10/2020","result":92,"consultedBy":6,"consultedAt":2},
{"id":712,"patientID":3,"date":"12/5/2020","result":46,"consultedBy":4,"consultedAt":2},
{"id":713,"patientID":76,"date":"12/27/2020","result":71,"consultedBy":9,"consultedAt":3},
{"id":714,"patientID":97,"date":"12/27/2020","result":33,"consultedBy":5,"consultedAt":4},
{"id":715,"patientID":10,"date":"12/26/2020","result":49,"consultedBy":5,"consultedAt":10},
{"id":716,"patientID":97,"date":"12/18/2020","result":52,"consultedBy":4,"consultedAt":10},
{"id":717,"patientID":85,"date":"1/1/2021","result":57,"consultedBy":10,"consultedAt":6},
{"id":718,"patientID":29,"date":"1/1/2021","result":65,"consultedBy":1,"consultedAt":8},
{"id":719,"patientID":38,"date":"12/16/2020","result":14,"consultedBy":7,"consultedAt":6},
{"id":720,"patientID":75,"date":"12/26/2020","result":75,"consultedBy":4,"consultedAt":8},
{"id":721,"patientID":94,"date":"12/5/2020","result":22,"consultedBy":8,"consultedAt":3},
{"id":722,"patientID":54,"date":"12/24/2020","result":56,"consultedBy":8,"consultedAt":2},
{"id":723,"patientID":41,"date":"12/4/2020","result":77,"consultedBy":2,"consultedAt":5},
{"id":724,"patientID":58,"date":"12/8/2020","result":63,"consultedBy":8,"consultedAt":3},
{"id":725,"patientID":19,"date":"12/19/2020","result":77,"consultedBy":2,"consultedAt":4},
{"id":726,"patientID":15,"date":"12/23/2020","result":26,"consultedBy":5,"consultedAt":3},
{"id":727,"patientID":67,"date":"12/22/2020","result":67,"consultedBy":9,"consultedAt":10},
{"id":728,"patientID":89,"date":"12/24/2020","result":88,"consultedBy":6,"consultedAt":1},
{"id":729,"patientID":90,"date":"12/24/2020","result":47,"consultedBy":1,"consultedAt":8},
{"id":730,"patientID":27,"date":"1/1/2021","result":36,"consultedBy":1,"consultedAt":3},
{"id":731,"patientID":97,"date":"12/7/2020","result":55,"consultedBy":3,"consultedAt":1},
{"id":732,"patientID":82,"date":"12/20/2020","result":75,"consultedBy":1,"consultedAt":9},
{"id":733,"patientID":70,"date":"12/18/2020","result":86,"consultedBy":1,"consultedAt":6},
{"id":734,"patientID":82,"date":"12/11/2020","result":3,"consultedBy":6,"consultedAt":10},
{"id":735,"patientID":66,"date":"12/17/2020","result":6,"consultedBy":6,"consultedAt":1},
{"id":736,"patientID":100,"date":"12/27/2020","result":70,"consultedBy":6,"consultedAt":8},
{"id":737,"patientID":32,"date":"12/24/2020","result":91,"consultedBy":5,"consultedAt":9},
{"id":738,"patientID":19,"date":"12/21/2020","result":14,"consultedBy":3,"consultedAt":5},
{"id":739,"patientID":77,"date":"12/31/2020","result":49,"consultedBy":2,"consultedAt":4},
{"id":740,"patientID":38,"date":"12/31/2020","result":88,"consultedBy":3,"consultedAt":10},
{"id":741,"patientID":12,"date":"12/12/2020","result":31,"consultedBy":5,"consultedAt":6},
{"id":742,"patientID":59,"date":"12/27/2020","result":6,"consultedBy":10,"consultedAt":9},
{"id":743,"patientID":76,"date":"12/1/2020","result":57,"consultedBy":4,"consultedAt":5},
{"id":744,"patientID":42,"date":"12/25/2020","result":41,"consultedBy":7,"consultedAt":4},
{"id":745,"patientID":15,"date":"12/4/2020","result":79,"consultedBy":5,"consultedAt":9},
{"id":746,"patientID":94,"date":"12/2/2020","result":37,"consultedBy":7,"consultedAt":1},
{"id":747,"patientID":91,"date":"12/31/2020","result":58,"consultedBy":3,"consultedAt":2},
{"id":748,"patientID":18,"date":"12/5/2020","result":49,"consultedBy":9,"consultedAt":1},
{"id":749,"patientID":56,"date":"12/24/2020","result":85,"consultedBy":9,"consultedAt":7},
{"id":750,"patientID":31,"date":"12/19/2020","result":16,"consultedBy":1,"consultedAt":7},
{"id":751,"patientID":32,"date":"12/29/2020","result":71,"consultedBy":2,"consultedAt":6},
{"id":752,"patientID":42,"date":"12/20/2020","result":14,"consultedBy":10,"consultedAt":10},
{"id":753,"patientID":16,"date":"12/10/2020","result":58,"consultedBy":5,"consultedAt":4},
{"id":754,"patientID":47,"date":"12/3/2020","result":54,"consultedBy":5,"consultedAt":9},
{"id":755,"patientID":77,"date":"12/26/2020","result":82,"consultedBy":10,"consultedAt":2},
{"id":756,"patientID":74,"date":"12/5/2020","result":99,"consultedBy":9,"consultedAt":3},
{"id":757,"patientID":55,"date":"12/30/2020","result":8,"consultedBy":4,"consultedAt":7},
{"id":758,"patientID":13,"date":"12/10/2020","result":9,"consultedBy":10,"consultedAt":4},
{"id":759,"patientID":18,"date":"12/13/2020","result":45,"consultedBy":4,"consultedAt":1},
{"id":760,"patientID":25,"date":"12/25/2020","result":21,"consultedBy":9,"consultedAt":7},
{"id":761,"patientID":67,"date":"12/12/2020","result":73,"consultedBy":9,"consultedAt":5},
{"id":762,"patientID":55,"date":"12/12/2020","result":29,"consultedBy":8,"consultedAt":4},
{"id":763,"patientID":73,"date":"12/7/2020","result":88,"consultedBy":3,"consultedAt":6},
{"id":764,"patientID":33,"date":"12/3/2020","result":74,"consultedBy":10,"consultedAt":6},
{"id":765,"patientID":55,"date":"12/19/2020","result":100,"consultedBy":2,"consultedAt":8},
{"id":766,"patientID":73,"date":"12/6/2020","result":65,"consultedBy":9,"consultedAt":7},
{"id":767,"patientID":56,"date":"12/17/2020","result":23,"consultedBy":1,"consultedAt":2},
{"id":768,"patientID":7,"date":"12/12/2020","result":96,"consultedBy":6,"consultedAt":8},
{"id":769,"patientID":23,"date":"12/12/2020","result":81,"consultedBy":7,"consultedAt":7},
{"id":770,"patientID":21,"date":"12/20/2020","result":30,"consultedBy":2,"consultedAt":7},
{"id":771,"patientID":18,"date":"12/24/2020","result":47,"consultedBy":2,"consultedAt":1},
{"id":772,"patientID":63,"date":"12/28/2020","result":41,"consultedBy":3,"consultedAt":8},
{"id":773,"patientID":90,"date":"12/13/2020","result":99,"consultedBy":5,"consultedAt":3},
{"id":774,"patientID":79,"date":"1/2/2021","result":99,"consultedBy":3,"consultedAt":8},
{"id":775,"patientID":17,"date":"12/19/2020","result":77,"consultedBy":5,"consultedAt":1},
{"id":776,"patientID":3,"date":"12/11/2020","result":21,"consultedBy":4,"consultedAt":9},
{"id":777,"patientID":68,"date":"12/22/2020","result":42,"consultedBy":2,"consultedAt":6},
{"id":778,"patientID":3,"date":"12/11/2020","result":55,"consultedBy":9,"consultedAt":9},
{"id":779,"patientID":50,"date":"12/16/2020","result":28,"consultedBy":1,"consultedAt":7},
{"id":780,"patientID":75,"date":"12/28/2020","result":80,"consultedBy":5,"consultedAt":7},
{"id":781,"patientID":29,"date":"12/24/2020","result":80,"consultedBy":2,"consultedAt":3},
{"id":782,"patientID":9,"date":"12/22/2020","result":1,"consultedBy":4,"consultedAt":3},
{"id":783,"patientID":89,"date":"12/28/2020","result":50,"consultedBy":4,"consultedAt":5},
{"id":784,"patientID":16,"date":"12/8/2020","result":98,"consultedBy":3,"consultedAt":1},
{"id":785,"patientID":43,"date":"12/4/2020","result":51,"consultedBy":1,"consultedAt":4},
{"id":786,"patientID":60,"date":"12/9/2020","result":62,"consultedBy":1,"consultedAt":5},
{"id":787,"patientID":95,"date":"12/31/2020","result":53,"consultedBy":1,"consultedAt":5},
{"id":788,"patientID":31,"date":"12/18/2020","result":22,"consultedBy":6,"consultedAt":2},
{"id":789,"patientID":97,"date":"12/5/2020","result":94,"consultedBy":4,"consultedAt":2},
{"id":790,"patientID":63,"date":"12/3/2020","result":89,"consultedBy":9,"consultedAt":2},
{"id":791,"patientID":92,"date":"12/26/2020","result":73,"consultedBy":2,"consultedAt":5},
{"id":792,"patientID":73,"date":"12/12/2020","result":96,"consultedBy":4,"consultedAt":8},
{"id":793,"patientID":55,"date":"12/13/2020","result":98,"consultedBy":7,"consultedAt":4},
{"id":794,"patientID":83,"date":"12/23/2020","result":41,"consultedBy":10,"consultedAt":8},
{"id":795,"patientID":58,"date":"12/21/2020","result":96,"consultedBy":9,"consultedAt":2},
{"id":796,"patientID":64,"date":"12/23/2020","result":98,"consultedBy":4,"consultedAt":5},
{"id":797,"patientID":57,"date":"12/1/2020","result":29,"consultedBy":5,"consultedAt":3},
{"id":798,"patientID":11,"date":"12/17/2020","result":57,"consultedBy":8,"consultedAt":3},
{"id":799,"patientID":66,"date":"12/18/2020","result":13,"consultedBy":9,"consultedAt":1},
{"id":800,"patientID":13,"date":"12/5/2020","result":6,"consultedBy":1,"consultedAt":6},
{"id":801,"patientID":71,"date":"12/21/2020","result":76,"consultedBy":2,"consultedAt":4},
{"id":802,"patientID":69,"date":"12/6/2020","result":59,"consultedBy":1,"consultedAt":7},
{"id":803,"patientID":90,"date":"12/13/2020","result":75,"consultedBy":4,"consultedAt":5},
{"id":804,"patientID":4,"date":"1/1/2021","result":98,"consultedBy":8,"consultedAt":9},
{"id":805,"patientID":79,"date":"12/15/2020","result":4,"consultedBy":4,"consultedAt":6},
{"id":806,"patientID":54,"date":"12/31/2020","result":98,"consultedBy":1,"consultedAt":7},
{"id":807,"patientID":15,"date":"12/15/2020","result":23,"consultedBy":6,"consultedAt":9},
{"id":808,"patientID":3,"date":"1/2/2021","result":60,"consultedBy":7,"consultedAt":3},
{"id":809,"patientID":17,"date":"12/22/2020","result":84,"consultedBy":8,"consultedAt":10},
{"id":810,"patientID":66,"date":"12/24/2020","result":89,"consultedBy":10,"consultedAt":5},
{"id":811,"patientID":45,"date":"12/8/2020","result":2,"consultedBy":5,"consultedAt":3},
{"id":812,"patientID":59,"date":"12/2/2020","result":64,"consultedBy":7,"consultedAt":2},
{"id":813,"patientID":89,"date":"12/31/2020","result":71,"consultedBy":4,"consultedAt":2},
{"id":814,"patientID":34,"date":"12/22/2020","result":68,"consultedBy":10,"consultedAt":1},
{"id":815,"patientID":79,"date":"12/5/2020","result":99,"consultedBy":6,"consultedAt":9},
{"id":816,"patientID":96,"date":"12/11/2020","result":80,"consultedBy":9,"consultedAt":7},
{"id":817,"patientID":76,"date":"12/10/2020","result":67,"consultedBy":1,"consultedAt":8},
{"id":818,"patientID":84,"date":"12/30/2020","result":68,"consultedBy":1,"consultedAt":2},
{"id":819,"patientID":6,"date":"12/10/2020","result":12,"consultedBy":6,"consultedAt":7},
{"id":820,"patientID":16,"date":"12/18/2020","result":21,"consultedBy":8,"consultedAt":7},
{"id":821,"patientID":89,"date":"12/18/2020","result":28,"consultedBy":10,"consultedAt":1},
{"id":822,"patientID":69,"date":"12/19/2020","result":58,"consultedBy":6,"consultedAt":8},
{"id":823,"patientID":32,"date":"12/6/2020","result":98,"consultedBy":1,"consultedAt":7},
{"id":824,"patientID":21,"date":"1/2/2021","result":75,"consultedBy":3,"consultedAt":1},
{"id":825,"patientID":43,"date":"12/19/2020","result":13,"consultedBy":8,"consultedAt":4},
{"id":826,"patientID":81,"date":"12/2/2020","result":34,"consultedBy":5,"consultedAt":3},
{"id":827,"patientID":44,"date":"12/22/2020","result":72,"consultedBy":4,"consultedAt":3},
{"id":828,"patientID":97,"date":"12/15/2020","result":85,"consultedBy":7,"consultedAt":6},
{"id":829,"patientID":59,"date":"12/23/2020","result":64,"consultedBy":10,"consultedAt":8},
{"id":830,"patientID":3,"date":"12/22/2020","result":57,"consultedBy":8,"consultedAt":7},
{"id":831,"patientID":28,"date":"12/16/2020","result":89,"consultedBy":4,"consultedAt":6},
{"id":832,"patientID":34,"date":"12/5/2020","result":82,"consultedBy":2,"consultedAt":1},
{"id":833,"patientID":17,"date":"12/11/2020","result":42,"consultedBy":2,"consultedAt":8},
{"id":834,"patientID":23,"date":"12/14/2020","result":60,"consultedBy":8,"consultedAt":2},
{"id":835,"patientID":1,"date":"12/15/2020","result":81,"consultedBy":1,"consultedAt":3},
{"id":836,"patientID":46,"date":"12/30/2020","result":56,"consultedBy":6,"consultedAt":9},
{"id":837,"patientID":30,"date":"12/13/2020","result":74,"consultedBy":1,"consultedAt":7},
{"id":838,"patientID":27,"date":"12/7/2020","result":82,"consultedBy":6,"consultedAt":8},
{"id":839,"patientID":7,"date":"12/7/2020","result":41,"consultedBy":2,"consultedAt":2},
{"id":840,"patientID":25,"date":"12/19/2020","result":22,"consultedBy":3,"consultedAt":10},
{"id":841,"patientID":8,"date":"12/10/2020","result":31,"consultedBy":8,"consultedAt":5},
{"id":842,"patientID":99,"date":"12/18/2020","result":52,"consultedBy":8,"consultedAt":7},
{"id":843,"patientID":32,"date":"12/11/2020","result":37,"consultedBy":3,"consultedAt":6},
{"id":844,"patientID":78,"date":"12/27/2020","result":22,"consultedBy":4,"consultedAt":3},
{"id":845,"patientID":66,"date":"12/31/2020","result":41,"consultedBy":2,"consultedAt":2},
{"id":846,"patientID":88,"date":"12/17/2020","result":53,"consultedBy":1,"consultedAt":8},
{"id":847,"patientID":83,"date":"12/4/2020","result":66,"consultedBy":9,"consultedAt":8},
{"id":848,"patientID":28,"date":"12/1/2020","result":90,"consultedBy":9,"consultedAt":9},
{"id":849,"patientID":47,"date":"12/3/2020","result":98,"consultedBy":1,"consultedAt":3},
{"id":850,"patientID":60,"date":"12/9/2020","result":84,"consultedBy":2,"consultedAt":8},
{"id":851,"patientID":46,"date":"12/29/2020","result":32,"consultedBy":6,"consultedAt":9},
{"id":852,"patientID":32,"date":"1/1/2021","result":37,"consultedBy":9,"consultedAt":6},
{"id":853,"patientID":64,"date":"12/21/2020","result":58,"consultedBy":3,"consultedAt":4},
{"id":854,"patientID":99,"date":"12/24/2020","result":2,"consultedBy":8,"consultedAt":2},
{"id":855,"patientID":36,"date":"12/30/2020","result":28,"consultedBy":5,"consultedAt":8},
{"id":856,"patientID":43,"date":"12/26/2020","result":11,"consultedBy":6,"consultedAt":7},
{"id":857,"patientID":55,"date":"12/29/2020","result":94,"consultedBy":9,"consultedAt":6},
{"id":858,"patientID":64,"date":"12/13/2020","result":75,"consultedBy":8,"consultedAt":5},
{"id":859,"patientID":34,"date":"12/25/2020","result":38,"consultedBy":5,"consultedAt":6},
{"id":860,"patientID":12,"date":"12/5/2020","result":51,"consultedBy":2,"consultedAt":8},
{"id":861,"patientID":54,"date":"12/9/2020","result":37,"consultedBy":6,"consultedAt":6},
{"id":862,"patientID":10,"date":"1/1/2021","result":43,"consultedBy":1,"consultedAt":4},
{"id":863,"patientID":73,"date":"12/19/2020","result":77,"consultedBy":2,"consultedAt":6},
{"id":864,"patientID":3,"date":"1/2/2021","result":47,"consultedBy":4,"consultedAt":5},
{"id":865,"patientID":38,"date":"12/11/2020","result":7,"consultedBy":9,"consultedAt":7},
{"id":866,"patientID":70,"date":"12/13/2020","result":63,"consultedBy":9,"consultedAt":1},
{"id":867,"patientID":18,"date":"12/17/2020","result":96,"consultedBy":7,"consultedAt":1},
{"id":868,"patientID":85,"date":"12/21/2020","result":14,"consultedBy":10,"consultedAt":6},
{"id":869,"patientID":32,"date":"12/18/2020","result":31,"consultedBy":7,"consultedAt":3},
{"id":870,"patientID":26,"date":"12/5/2020","result":85,"consultedBy":10,"consultedAt":10},
{"id":871,"patientID":16,"date":"12/8/2020","result":59,"consultedBy":4,"consultedAt":2},
{"id":872,"patientID":29,"date":"12/9/2020","result":69,"consultedBy":8,"consultedAt":2},
{"id":873,"patientID":88,"date":"12/13/2020","result":69,"consultedBy":6,"consultedAt":7},
{"id":874,"patientID":71,"date":"12/11/2020","result":25,"consultedBy":4,"consultedAt":4},
{"id":875,"patientID":52,"date":"12/2/2020","result":64,"consultedBy":2,"consultedAt":10},
{"id":876,"patientID":28,"date":"12/19/2020","result":88,"consultedBy":1,"consultedAt":10},
{"id":877,"patientID":32,"date":"12/19/2020","result":29,"consultedBy":10,"consultedAt":10},
{"id":878,"patientID":74,"date":"12/15/2020","result":56,"consultedBy":5,"consultedAt":9},
{"id":879,"patientID":92,"date":"12/15/2020","result":29,"consultedBy":2,"consultedAt":5},
{"id":880,"patientID":84,"date":"1/1/2021","result":13,"consultedBy":3,"consultedAt":9},
{"id":881,"patientID":68,"date":"12/17/2020","result":67,"consultedBy":5,"consultedAt":9},
{"id":882,"patientID":64,"date":"1/1/2021","result":44,"consultedBy":6,"consultedAt":4},
{"id":883,"patientID":51,"date":"12/2/2020","result":67,"consultedBy":10,"consultedAt":3},
{"id":884,"patientID":9,"date":"12/7/2020","result":74,"consultedBy":10,"consultedAt":7},
{"id":885,"patientID":59,"date":"12/17/2020","result":55,"consultedBy":1,"consultedAt":10},
{"id":886,"patientID":86,"date":"12/28/2020","result":59,"consultedBy":8,"consultedAt":2},
{"id":887,"patientID":80,"date":"12/28/2020","result":71,"consultedBy":5,"consultedAt":5},
{"id":888,"patientID":86,"date":"12/21/2020","result":15,"consultedBy":8,"consultedAt":4},
{"id":889,"patientID":15,"date":"12/31/2020","result":95,"consultedBy":9,"consultedAt":7},
{"id":890,"patientID":61,"date":"12/30/2020","result":83,"consultedBy":9,"consultedAt":1},
{"id":891,"patientID":69,"date":"12/25/2020","result":33,"consultedBy":6,"consultedAt":4},
{"id":892,"patientID":60,"date":"12/31/2020","result":36,"consultedBy":8,"consultedAt":4},
{"id":893,"patientID":55,"date":"12/22/2020","result":95,"consultedBy":7,"consultedAt":7},
{"id":894,"patientID":47,"date":"12/13/2020","result":75,"consultedBy":10,"consultedAt":9},
{"id":895,"patientID":50,"date":"12/25/2020","result":71,"consultedBy":1,"consultedAt":5},
{"id":896,"patientID":66,"date":"12/6/2020","result":2,"consultedBy":7,"consultedAt":7},
{"id":897,"patientID":97,"date":"12/20/2020","result":99,"consultedBy":9,"consultedAt":1},
{"id":898,"patientID":87,"date":"12/22/2020","result":82,"consultedBy":3,"consultedAt":3},
{"id":899,"patientID":2,"date":"12/26/2020","result":17,"consultedBy":7,"consultedAt":2},
{"id":900,"patientID":69,"date":"12/21/2020","result":91,"consultedBy":4,"consultedAt":4},
{"id":901,"patientID":66,"date":"1/2/2021","result":32,"consultedBy":5,"consultedAt":2},
{"id":902,"patientID":92,"date":"12/16/2020","result":60,"consultedBy":8,"consultedAt":3},
{"id":903,"patientID":21,"date":"1/1/2021","result":18,"consultedBy":9,"consultedAt":7},
{"id":904,"patientID":1,"date":"1/1/2021","result":3,"consultedBy":7,"consultedAt":6},
{"id":905,"patientID":36,"date":"12/17/2020","result":57,"consultedBy":2,"consultedAt":10},
{"id":906,"patientID":32,"date":"12/4/2020","result":16,"consultedBy":2,"consultedAt":4},
{"id":907,"patientID":11,"date":"12/12/2020","result":45,"consultedBy":4,"consultedAt":9},
{"id":908,"patientID":91,"date":"12/20/2020","result":8,"consultedBy":8,"consultedAt":5},
{"id":909,"patientID":92,"date":"12/7/2020","result":54,"consultedBy":5,"consultedAt":4},
{"id":910,"patientID":69,"date":"12/9/2020","result":97,"consultedBy":5,"consultedAt":4},
{"id":911,"patientID":56,"date":"1/1/2021","result":46,"consultedBy":8,"consultedAt":2},
{"id":912,"patientID":83,"date":"12/15/2020","result":22,"consultedBy":5,"consultedAt":10},
{"id":913,"patientID":75,"date":"12/28/2020","result":92,"consultedBy":9,"consultedAt":3},
{"id":914,"patientID":17,"date":"12/8/2020","result":40,"consultedBy":1,"consultedAt":5},
{"id":915,"patientID":57,"date":"12/30/2020","result":91,"consultedBy":10,"consultedAt":10},
{"id":916,"patientID":23,"date":"12/5/2020","result":25,"consultedBy":8,"consultedAt":5},
{"id":917,"patientID":9,"date":"12/15/2020","result":78,"consultedBy":10,"consultedAt":2},
{"id":918,"patientID":17,"date":"12/5/2020","result":60,"consultedBy":1,"consultedAt":3},
{"id":919,"patientID":44,"date":"12/10/2020","result":59,"consultedBy":5,"consultedAt":5},
{"id":920,"patientID":4,"date":"12/6/2020","result":65,"consultedBy":1,"consultedAt":2},
{"id":921,"patientID":56,"date":"12/16/2020","result":21,"consultedBy":5,"consultedAt":10},
{"id":922,"patientID":21,"date":"12/25/2020","result":62,"consultedBy":4,"consultedAt":7},
{"id":923,"patientID":80,"date":"12/25/2020","result":35,"consultedBy":6,"consultedAt":2},
{"id":924,"patientID":26,"date":"12/19/2020","result":68,"consultedBy":1,"consultedAt":1},
{"id":925,"patientID":93,"date":"12/27/2020","result":71,"consultedBy":7,"consultedAt":4},
{"id":926,"patientID":22,"date":"12/15/2020","result":76,"consultedBy":6,"consultedAt":3},
{"id":927,"patientID":96,"date":"12/13/2020","result":9,"consultedBy":6,"consultedAt":8},
{"id":928,"patientID":68,"date":"12/24/2020","result":68,"consultedBy":10,"consultedAt":9},
{"id":929,"patientID":26,"date":"12/28/2020","result":9,"consultedBy":1,"consultedAt":9},
{"id":930,"patientID":74,"date":"12/13/2020","result":32,"consultedBy":9,"consultedAt":1},
{"id":931,"patientID":46,"date":"1/2/2021","result":46,"consultedBy":4,"consultedAt":9},
{"id":932,"patientID":59,"date":"12/20/2020","result":39,"consultedBy":5,"consultedAt":7},
{"id":933,"patientID":54,"date":"1/2/2021","result":7,"consultedBy":7,"consultedAt":9},
{"id":934,"patientID":11,"date":"12/27/2020","result":12,"consultedBy":6,"consultedAt":4},
{"id":935,"patientID":2,"date":"12/5/2020","result":100,"consultedBy":3,"consultedAt":3},
{"id":936,"patientID":43,"date":"12/10/2020","result":24,"consultedBy":10,"consultedAt":4},
{"id":937,"patientID":27,"date":"12/12/2020","result":73,"consultedBy":7,"consultedAt":2},
{"id":938,"patientID":5,"date":"12/14/2020","result":32,"consultedBy":7,"consultedAt":8},
{"id":939,"patientID":76,"date":"12/13/2020","result":82,"consultedBy":6,"consultedAt":9},
{"id":940,"patientID":56,"date":"12/19/2020","result":72,"consultedBy":5,"consultedAt":3},
{"id":941,"patientID":92,"date":"12/19/2020","result":28,"consultedBy":3,"consultedAt":8},
{"id":942,"patientID":49,"date":"12/8/2020","result":15,"consultedBy":6,"consultedAt":6},
{"id":943,"patientID":1,"date":"12/2/2020","result":52,"consultedBy":9,"consultedAt":9},
{"id":944,"patientID":62,"date":"12/22/2020","result":41,"consultedBy":9,"consultedAt":8},
{"id":945,"patientID":16,"date":"12/30/2020","result":47,"consultedBy":7,"consultedAt":2},
{"id":946,"patientID":93,"date":"12/22/2020","result":44,"consultedBy":4,"consultedAt":6},
{"id":947,"patientID":90,"date":"1/1/2021","result":41,"consultedBy":4,"consultedAt":10},
{"id":948,"patientID":9,"date":"12/5/2020","result":17,"consultedBy":1,"consultedAt":3},
{"id":949,"patientID":29,"date":"12/1/2020","result":13,"consultedBy":7,"consultedAt":5},
{"id":950,"patientID":3,"date":"12/29/2020","result":40,"consultedBy":8,"consultedAt":2},
{"id":951,"patientID":8,"date":"12/10/2020","result":52,"consultedBy":6,"consultedAt":6},
{"id":952,"patientID":17,"date":"12/1/2020","result":35,"consultedBy":1,"consultedAt":9},
{"id":953,"patientID":65,"date":"12/16/2020","result":1,"consultedBy":8,"consultedAt":1},
{"id":954,"patientID":64,"date":"12/14/2020","result":55,"consultedBy":10,"consultedAt":1},
{"id":955,"patientID":17,"date":"12/14/2020","result":17,"consultedBy":4,"consultedAt":2},
{"id":956,"patientID":6,"date":"12/10/2020","result":64,"consultedBy":5,"consultedAt":6},
{"id":957,"patientID":52,"date":"12/26/2020","result":68,"consultedBy":2,"consultedAt":3},
{"id":958,"patientID":94,"date":"12/2/2020","result":43,"consultedBy":1,"consultedAt":10},
{"id":959,"patientID":59,"date":"12/23/2020","result":47,"consultedBy":1,"consultedAt":2},
{"id":960,"patientID":23,"date":"12/31/2020","result":31,"consultedBy":2,"consultedAt":5},
{"id":961,"patientID":30,"date":"12/6/2020","result":91,"consultedBy":2,"consultedAt":2},
{"id":962,"patientID":73,"date":"12/26/2020","result":40,"consultedBy":2,"consultedAt":5},
{"id":963,"patientID":5,"date":"12/26/2020","result":45,"consultedBy":3,"consultedAt":7},
{"id":964,"patientID":91,"date":"12/28/2020","result":81,"consultedBy":7,"consultedAt":2},
{"id":965,"patientID":30,"date":"12/1/2020","result":70,"consultedBy":9,"consultedAt":1},
{"id":966,"patientID":97,"date":"12/17/2020","result":96,"consultedBy":8,"consultedAt":10},
{"id":967,"patientID":56,"date":"12/23/2020","result":29,"consultedBy":9,"consultedAt":10},
{"id":968,"patientID":17,"date":"12/5/2020","result":52,"consultedBy":1,"consultedAt":3},
{"id":969,"patientID":60,"date":"12/21/2020","result":36,"consultedBy":2,"consultedAt":8},
{"id":970,"patientID":17,"date":"1/2/2021","result":46,"consultedBy":2,"consultedAt":9},
{"id":971,"patientID":31,"date":"12/31/2020","result":21,"consultedBy":6,"consultedAt":3},
{"id":972,"patientID":55,"date":"12/29/2020","result":28,"consultedBy":7,"consultedAt":7},
{"id":973,"patientID":80,"date":"12/11/2020","result":11,"consultedBy":3,"consultedAt":10},
{"id":974,"patientID":42,"date":"12/14/2020","result":55,"consultedBy":8,"consultedAt":1},
{"id":975,"patientID":26,"date":"12/13/2020","result":56,"consultedBy":10,"consultedAt":8},
{"id":976,"patientID":60,"date":"12/19/2020","result":94,"consultedBy":3,"consultedAt":7},
{"id":977,"patientID":91,"date":"12/27/2020","result":80,"consultedBy":3,"consultedAt":4},
{"id":978,"patientID":26,"date":"12/17/2020","result":58,"consultedBy":2,"consultedAt":10},
{"id":979,"patientID":49,"date":"12/30/2020","result":45,"consultedBy":4,"consultedAt":4},
{"id":980,"patientID":23,"date":"12/3/2020","result":45,"consultedBy":7,"consultedAt":3},
{"id":981,"patientID":20,"date":"12/2/2020","result":98,"consultedBy":4,"consultedAt":7},
{"id":982,"patientID":99,"date":"12/8/2020","result":57,"consultedBy":1,"consultedAt":5},
{"id":983,"patientID":55,"date":"12/13/2020","result":26,"consultedBy":8,"consultedAt":7},
{"id":984,"patientID":38,"date":"12/26/2020","result":18,"consultedBy":8,"consultedAt":2},
{"id":985,"patientID":32,"date":"1/2/2021","result":47,"consultedBy":8,"consultedAt":3},
{"id":986,"patientID":7,"date":"12/19/2020","result":66,"consultedBy":3,"consultedAt":8},
{"id":987,"patientID":65,"date":"12/13/2020","result":74,"consultedBy":6,"consultedAt":4},
{"id":988,"patientID":62,"date":"12/29/2020","result":45,"consultedBy":8,"consultedAt":1},
{"id":989,"patientID":37,"date":"12/6/2020","result":21,"consultedBy":1,"consultedAt":8},
{"id":990,"patientID":94,"date":"1/1/2021","result":95,"consultedBy":6,"consultedAt":8},
{"id":991,"patientID":99,"date":"12/8/2020","result":72,"consultedBy":3,"consultedAt":9},
{"id":992,"patientID":92,"date":"12/5/2020","result":50,"consultedBy":6,"consultedAt":7},
{"id":993,"patientID":83,"date":"12/7/2020","result":65,"consultedBy":6,"consultedAt":9},
{"id":994,"patientID":23,"date":"12/3/2020","result":18,"consultedBy":7,"consultedAt":9},
{"id":995,"patientID":36,"date":"12/15/2020","result":1,"consultedBy":3,"consultedAt":1},
{"id":996,"patientID":17,"date":"12/8/2020","result":39,"consultedBy":6,"consultedAt":10},
{"id":997,"patientID":62,"date":"12/19/2020","result":34,"consultedBy":9,"consultedAt":5},
{"id":998,"patientID":52,"date":"1/1/2021","result":8,"consultedBy":2,"consultedAt":6},
{"id":999,"patientID":25,"date":"12/24/2020","result":48,"consultedBy":9,"consultedAt":9},
{"id":1000,"patientID":24,"date":"12/17/2020","result":55,"consultedBy":10,"consultedAt":2}]